{"add":{"path":"instance_name=pr136.tsp/k_factor=SMALL/has_closed_cycle=true/191-4f730fe3-191e-444b-9c94-6d4d0966ea62-0.parquet","partitionValues":{"has_closed_cycle":"true","instance_name":"pr136.tsp","k_factor":"SMALL"},"size":3667,"modificationTime":1748998940504,"dataChange":true,"stats":"{\"numRecords\": 135, \"minValues\": {\"path_vertices.list.item\": 1, \"path_length\": 27247}, \"maxValues\": {\"path_vertices.list.item\": 136, \"path_length\": 34043}, \"nullCount\": {\"path_vertices.list.item\": 0, \"path_length\": 0}}","tags":null,"deletionVector":null,"baseRowId":null,"defaultRowCommitVersion":null,"clusteringProvider":null}}
{"commitInfo":{"timestamp":1748998940504,"operation":"WRITE","operationParameters":{"mode":"Append","partitionBy":"[\"instance_name\",\"k_factor\",\"has_closed_cycle\"]"},"clientVersion":"delta-rs.0.17.3"}}