{"add":{"path":"instance_name=kroA100.tsp/k_factor=MEDIUM/has_closed_cycle=false/113-aee3eed7-4aa6-45d7-8b54-f3cd09959e5c-0.parquet","partitionValues":{"instance_name":"kroA100.tsp","k_factor":"MEDIUM","has_closed_cycle":"false"},"size":4287,"modificationTime":1748998877487,"dataChange":true,"stats":"{\"numRecords\": 99, \"minValues\": {\"path_vertices.list.item\": 1, \"path_length\": 8762}, \"maxValues\": {\"path_vertices.list.item\": 100, \"path_length\": 13724}, \"nullCount\": {\"path_vertices.list.item\": 0, \"path_length\": 0}}","tags":null,"deletionVector":null,"baseRowId":null,"defaultRowCommitVersion":null,"clusteringProvider":null}}
{"commitInfo":{"timestamp":1748998877488,"operation":"WRITE","operationParameters":{"mode":"Append","partitionBy":"[\"instance_name\",\"k_factor\",\"has_closed_cycle\"]"},"clientVersion":"delta-rs.0.17.3"}}