{"add":{"path":"instance_name=gr21.tsp/k_factor=LARGE/has_closed_cycle=false/53-cbeb36aa-4b36-4b6f-9fcc-435a8d3118da-0.parquet","partitionValues":{"has_closed_cycle":"false","instance_name":"gr21.tsp","k_factor":"LARGE"},"size":1396,"modificationTime":1748998870431,"dataChange":true,"stats":"{\"numRecords\": 20, \"minValues\": {\"path_vertices.list.item\": 0, \"path_length\": 1251}, \"maxValues\": {\"path_vertices.list.item\": 20, \"path_length\": 1968}, \"nullCount\": {\"path_vertices.list.item\": 0, \"path_length\": 0}}","tags":null,"deletionVector":null,"baseRowId":null,"defaultRowCommitVersion":null,"clusteringProvider":null}}
{"commitInfo":{"timestamp":1748998870431,"operation":"WRITE","operationParameters":{"mode":"Append","partitionBy":"[\"instance_name\",\"k_factor\",\"has_closed_cycle\"]"},"clientVersion":"delta-rs.0.17.3"}}