{"protocol":{"minReaderVersion":1,"minWriterVersion":2}}
{"metaData":{"id":"fb06f750-5b3c-4f21-9d9e-6cbc5b1a9c65","name":null,"description":null,"format":{"provider":"parquet","options":{}},"schemaString":"{\"type\":\"struct\",\"fields\":[{\"name\":\"experiment_id\",\"type\":\"string\",\"nullable\":true,\"metadata\":{}},{\"name\":\"experiment_name\",\"type\":\"string\",\"nullable\":true,\"metadata\":{}},{\"name\":\"instance_name\",\"type\":\"string\",\"nullable\":true,\"metadata\":{}},{\"name\":\"k_factor\",\"type\":\"double\",\"nullable\":true,\"metadata\":{}},{\"name\":\"repetitions\",\"type\":\"long\",\"nullable\":true,\"metadata\":{}},{\"name\":\"model_name\",\"type\":\"string\",\"nullable\":true,\"metadata\":{}},{\"name\":\"has_closed_cycle\",\"type\":\"boolean\",\"nullable\":true,\"metadata\":{}},{\"name\":\"session_id\",\"type\":\"string\",\"nullable\":true,\"metadata\":{}},{\"name\":\"instance\",\"type\":{\"type\":\"struct\",\"fields\":[{\"name\":\"name\",\"type\":\"string\",\"nullable\":true,\"metadata\":{}},{\"name\":\"number_of_edges\",\"type\":\"long\",\"nullable\":true,\"metadata\":{}},{\"name\":\"number_of_vertices\",\"type\":\"long\",\"nullable\":true,\"metadata\":{}},{\"name\":\"symmetrical_type\",\"type\":\"string\",\"nullable\":true,\"metadata\":{}}]},\"nullable\":true,\"metadata\":{}},{\"name\":\"model\",\"type\":{\"type\":\"struct\",\"fields\":[{\"name\":\"generations\",\"type\":\"long\",\"nullable\":true,\"metadata\":{}},{\"name\":\"mutation_operator_probabilities\",\"type\":{\"type\":\"array\",\"elementType\":\"double\",\"containsNull\":true},\"nullable\":true,\"metadata\":{}},{\"name\":\"mutation_rate\",\"type\":\"double\",\"nullable\":true,\"metadata\":{}},{\"name\":\"name\",\"type\":\"string\",\"nullable\":true,\"metadata\":{}},{\"name\":\"population_size\",\"type\":\"long\",\"nullable\":true,\"metadata\":{}},{\"name\":\"selection_size\",\"type\":\"long\",\"nullable\":true,\"metadata\":{}},{\"name\":\"use_crossover\",\"type\":\"boolean\",\"nullable\":true,\"metadata\":{}}]},\"nullable\":true,\"metadata\":{}},{\"name\":\"path_vertices\",\"type\":{\"type\":\"array\",\"elementType\":\"long\",\"containsNull\":true},\"nullable\":true,\"metadata\":{}},{\"name\":\"path_length\",\"type\":\"long\",\"nullable\":true,\"metadata\":{}},{\"name\":\"k_size\",\"type\":\"long\",\"nullable\":true,\"metadata\":{}}]}","partitionColumns":["instance_name","k_factor","has_closed_cycle","model_name"],"createdTime":1749176696583,"configuration":{}}}
{"add":{"path":"instance_name=brazil58.tsp/k_factor=0.25/has_closed_cycle=false/model_name=GeneticAlgorithmNearestNeighborsEnsemble/0-7840e4a7-a3e7-4249-a65b-7ea520974647-0.parquet","partitionValues":{"k_factor":"0.25","has_closed_cycle":"false","model_name":"GeneticAlgorithmNearestNeighborsEnsemble","instance_name":"brazil58.tsp"},"size":8839,"modificationTime":1749176696582,"dataChange":true,"stats":"{\"numRecords\": 30, \"minValues\": {\"experiment_id\": \"6cfaf924-427d-11f0-879d-7cc25567a3b2\", \"experiment_name\": \"change__ordered_crossover\", \"repetitions\": 30, \"session_id\": \"6d9637fe-427d-11f0-879d-7cc25567a3b2\", \"instance.name\": \"brazil58.tsp\", \"instance.number_of_edges\": 1711, \"instance.number_of_vertices\": 58, \"instance.symmetrical_type\": \"TSP\", \"model.generations\": 100, \"model.mutation_operator_probabilities.list.item\": -0.0, \"model.mutation_rate\": 0.01, \"model.name\": \"GeneticAlgorithmNearestNeighborsEnsemble\", \"model.population_size\": 100, \"model.selection_size\": 10, \"model.use_crossover\": true, \"path_vertices.list.item\": 1, \"path_length\": 1914, \"k_size\": 14}, \"maxValues\": {\"experiment_id\": \"6cfaf924-427d-11f0-879d-7cc25567a3b2\", \"experiment_name\": \"change__ordered_crossover\", \"repetitions\": 30, \"session_id\": \"6ffddace-427d-11f0-879d-7cc25567a3b2\", \"instance.name\": \"brazil58.tsp\", \"instance.number_of_edges\": 1711, \"instance.number_of_vertices\": 58, \"instance.symmetrical_type\": \"TSP\", \"model.generations\": 100, \"model.mutation_operator_probabilities.list.item\": 0.3333333333333333, \"model.mutation_rate\": 0.01, \"model.name\": \"GeneticAlgorithmNearestNeighborsEnsemble\", \"model.population_size\": 100, \"model.selection_size\": 10, \"model.use_crossover\": true, \"path_vertices.list.item\": 54, \"path_length\": 1978, \"k_size\": 14}, \"nullCount\": {\"experiment_id\": 0, \"experiment_name\": 0, \"repetitions\": 0, \"session_id\": 0, \"instance.name\": 0, \"instance.number_of_edges\": 0, \"instance.number_of_vertices\": 0, \"instance.symmetrical_type\": 0, \"model.generations\": 28, \"model.mutation_operator_probabilities.list.item\": 28, \"model.mutation_rate\": 28, \"model.name\": 0, \"model.population_size\": 28, \"model.selection_size\": 28, \"model.use_crossover\": 28, \"path_vertices.list.item\": 0, \"path_length\": 0, \"k_size\": 0}}","tags":null,"deletionVector":null,"baseRowId":null,"defaultRowCommitVersion":null,"clusteringProvider":null}}
{"commitInfo":{"timestamp":1749176696583,"operation":"CREATE TABLE","operationParameters":{"mode":"ErrorIfExists","location":"file:///home/leonichel/k-tsp-solver/results/change__ordered_crossover/6cfaf924-427d-11f0-879d-7cc25567a3b2","metadata":"{\"configuration\":{},\"createdTime\":1749176696583,\"description\":null,\"format\":{\"options\":{},\"provider\":\"parquet\"},\"id\":\"fb06f750-5b3c-4f21-9d9e-6cbc5b1a9c65\",\"name\":null,\"partitionColumns\":[\"instance_name\",\"k_factor\",\"has_closed_cycle\",\"model_name\"],\"schemaString\":\"{\\\"type\\\":\\\"struct\\\",\\\"fields\\\":[{\\\"name\\\":\\\"experiment_id\\\",\\\"type\\\":\\\"string\\\",\\\"nullable\\\":true,\\\"metadata\\\":{}},{\\\"name\\\":\\\"experiment_name\\\",\\\"type\\\":\\\"string\\\",\\\"nullable\\\":true,\\\"metadata\\\":{}},{\\\"name\\\":\\\"instance_name\\\",\\\"type\\\":\\\"string\\\",\\\"nullable\\\":true,\\\"metadata\\\":{}},{\\\"name\\\":\\\"k_factor\\\",\\\"type\\\":\\\"double\\\",\\\"nullable\\\":true,\\\"metadata\\\":{}},{\\\"name\\\":\\\"repetitions\\\",\\\"type\\\":\\\"long\\\",\\\"nullable\\\":true,\\\"metadata\\\":{}},{\\\"name\\\":\\\"model_name\\\",\\\"type\\\":\\\"string\\\",\\\"nullable\\\":true,\\\"metadata\\\":{}},{\\\"name\\\":\\\"has_closed_cycle\\\",\\\"type\\\":\\\"boolean\\\",\\\"nullable\\\":true,\\\"metadata\\\":{}},{\\\"name\\\":\\\"session_id\\\",\\\"type\\\":\\\"string\\\",\\\"nullable\\\":true,\\\"metadata\\\":{}},{\\\"name\\\":\\\"instance\\\",\\\"type\\\":{\\\"type\\\":\\\"struct\\\",\\\"fields\\\":[{\\\"name\\\":\\\"name\\\",\\\"type\\\":\\\"string\\\",\\\"nullable\\\":true,\\\"metadata\\\":{}},{\\\"name\\\":\\\"number_of_edges\\\",\\\"type\\\":\\\"long\\\",\\\"nullable\\\":true,\\\"metadata\\\":{}},{\\\"name\\\":\\\"number_of_vertices\\\",\\\"type\\\":\\\"long\\\",\\\"nullable\\\":true,\\\"metadata\\\":{}},{\\\"name\\\":\\\"symmetrical_type\\\",\\\"type\\\":\\\"string\\\",\\\"nullable\\\":true,\\\"metadata\\\":{}}]},\\\"nullable\\\":true,\\\"metadata\\\":{}},{\\\"name\\\":\\\"model\\\",\\\"type\\\":{\\\"type\\\":\\\"struct\\\",\\\"fields\\\":[{\\\"name\\\":\\\"generations\\\",\\\"type\\\":\\\"long\\\",\\\"nullable\\\":true,\\\"metadata\\\":{}},{\\\"name\\\":\\\"mutation_operator_probabilities\\\",\\\"type\\\":{\\\"type\\\":\\\"array\\\",\\\"elementType\\\":\\\"double\\\",\\\"containsNull\\\":true},\\\"nullable\\\":true,\\\"metadata\\\":{}},{\\\"name\\\":\\\"mutation_rate\\\",\\\"type\\\":\\\"double\\\",\\\"nullable\\\":true,\\\"metadata\\\":{}},{\\\"name\\\":\\\"name\\\",\\\"type\\\":\\\"string\\\",\\\"nullable\\\":true,\\\"metadata\\\":{}},{\\\"name\\\":\\\"population_size\\\",\\\"type\\\":\\\"long\\\",\\\"nullable\\\":true,\\\"metadata\\\":{}},{\\\"name\\\":\\\"selection_size\\\",\\\"type\\\":\\\"long\\\",\\\"nullable\\\":true,\\\"metadata\\\":{}},{\\\"name\\\":\\\"use_crossover\\\",\\\"type\\\":\\\"boolean\\\",\\\"nullable\\\":true,\\\"metadata\\\":{}}]},\\\"nullable\\\":true,\\\"metadata\\\":{}},{\\\"name\\\":\\\"path_vertices\\\",\\\"type\\\":{\\\"type\\\":\\\"array\\\",\\\"elementType\\\":\\\"long\\\",\\\"containsNull\\\":true},\\\"nullable\\\":true,\\\"metadata\\\":{}},{\\\"name\\\":\\\"path_length\\\",\\\"type\\\":\\\"long\\\",\\\"nullable\\\":true,\\\"metadata\\\":{}},{\\\"name\\\":\\\"k_size\\\",\\\"type\\\":\\\"long\\\",\\\"nullable\\\":true,\\\"metadata\\\":{}}]}\"}","protocol":"{\"minReaderVersion\":1,\"minWriterVersion\":2}"},"clientVersion":"delta-rs.0.17.3"}}