{"protocol":{"minReaderVersion":1,"minWriterVersion":2}}
{"metaData":{"id":"a10bfb70-0f65-4028-a5ab-d87525dceb52","name":null,"description":null,"format":{"provider":"parquet","options":{}},"schemaString":"{\"type\":\"struct\",\"fields\":[{\"name\":\"experiment_id\",\"type\":\"string\",\"nullable\":true,\"metadata\":{}},{\"name\":\"experiment_name\",\"type\":\"string\",\"nullable\":true,\"metadata\":{}},{\"name\":\"instance_name\",\"type\":\"string\",\"nullable\":true,\"metadata\":{}},{\"name\":\"k_factor\",\"type\":\"double\",\"nullable\":true,\"metadata\":{}},{\"name\":\"repetitions\",\"type\":\"long\",\"nullable\":true,\"metadata\":{}},{\"name\":\"model_name\",\"type\":\"string\",\"nullable\":true,\"metadata\":{}},{\"name\":\"has_closed_cycle\",\"type\":\"boolean\",\"nullable\":true,\"metadata\":{}},{\"name\":\"session_id\",\"type\":\"string\",\"nullable\":true,\"metadata\":{}},{\"name\":\"instance\",\"type\":{\"type\":\"struct\",\"fields\":[{\"name\":\"name\",\"type\":\"string\",\"nullable\":true,\"metadata\":{}},{\"name\":\"number_of_edges\",\"type\":\"long\",\"nullable\":true,\"metadata\":{}},{\"name\":\"number_of_vertices\",\"type\":\"long\",\"nullable\":true,\"metadata\":{}},{\"name\":\"symmetrical_type\",\"type\":\"string\",\"nullable\":true,\"metadata\":{}}]},\"nullable\":true,\"metadata\":{}},{\"name\":\"model\",\"type\":{\"type\":\"struct\",\"fields\":[{\"name\":\"generations\",\"type\":\"long\",\"nullable\":true,\"metadata\":{}},{\"name\":\"mutation_operator_probabilities\",\"type\":{\"type\":\"array\",\"elementType\":\"double\",\"containsNull\":true},\"nullable\":true,\"metadata\":{}},{\"name\":\"mutation_rate\",\"type\":\"double\",\"nullable\":true,\"metadata\":{}},{\"name\":\"name\",\"type\":\"string\",\"nullable\":true,\"metadata\":{}},{\"name\":\"population_size\",\"type\":\"long\",\"nullable\":true,\"metadata\":{}},{\"name\":\"selection_size\",\"type\":\"long\",\"nullable\":true,\"metadata\":{}},{\"name\":\"use_crossover\",\"type\":\"boolean\",\"nullable\":true,\"metadata\":{}}]},\"nullable\":true,\"metadata\":{}},{\"name\":\"path_vertices\",\"type\":{\"type\":\"array\",\"elementType\":\"long\",\"containsNull\":true},\"nullable\":true,\"metadata\":{}},{\"name\":\"path_length\",\"type\":\"long\",\"nullable\":true,\"metadata\":{}},{\"name\":\"k_size\",\"type\":\"long\",\"nullable\":true,\"metadata\":{}}]}","partitionColumns":["instance_name","k_factor","has_closed_cycle","model_name"],"createdTime":1749572665542,"configuration":{}}}
{"add":{"path":"instance_name=att532.tsp/k_factor=0.25/has_closed_cycle=true/model_name=GeneticAlgorithmNearestNeighborsEnsemble/0-e0b2688e-1038-4cba-8064-8b83512db48e-0.parquet","partitionValues":{"instance_name":"att532.tsp","k_factor":"0.25","has_closed_cycle":"true","model_name":"GeneticAlgorithmNearestNeighborsEnsemble"},"size":9142,"modificationTime":1749572665541,"dataChange":true,"stats":"{\"numRecords\": 1, \"minValues\": {\"experiment_id\": \"2f541d89-4617-11f0-b9b3-631adf8121e0\", \"experiment_name\": \"hyperparameter_tuning__grouped_bayesian_search\", \"repetitions\": 1, \"session_id\": \"5fde5496-4617-11f0-b9b3-631adf8121e0\", \"instance.name\": \"att532.tsp\", \"instance.number_of_edges\": 141778, \"instance.number_of_vertices\": 532, \"instance.symmetrical_type\": \"TSP\", \"model.generations\": 204, \"model.mutation_operator_probabilities.list.item\": 0.09165753816697864, \"model.mutation_rate\": 0.47729999999999995, \"model.name\": \"GeneticAlgorithmNearestNeighborsEnsemble\", \"model.population_size\": 375, \"model.selection_size\": 308, \"model.use_crossover\": true, \"path_vertices.list.item\": 1, \"path_length\": 5038, \"k_size\": 133}, \"maxValues\": {\"experiment_id\": \"2f541d89-4617-11f0-b9b3-631adf8121e0\", \"experiment_name\": \"hyperparameter_tuning__grouped_bayesian_search\", \"repetitions\": 1, \"session_id\": \"5fde5496-4617-11f0-b9b3-631adf8121e0\", \"instance.name\": \"att532.tsp\", \"instance.number_of_edges\": 141778, \"instance.number_of_vertices\": 532, \"instance.symmetrical_type\": \"TSP\", \"model.generations\": 204, \"model.mutation_operator_probabilities.list.item\": 0.5561265671252138, \"model.mutation_rate\": 0.47729999999999995, \"model.name\": \"GeneticAlgorithmNearestNeighborsEnsemble\", \"model.population_size\": 375, \"model.selection_size\": 308, \"model.use_crossover\": true, \"path_vertices.list.item\": 310, \"path_length\": 5038, \"k_size\": 133}, \"nullCount\": {\"experiment_id\": 0, \"experiment_name\": 0, \"repetitions\": 0, \"session_id\": 0, \"instance.name\": 0, \"instance.number_of_edges\": 0, \"instance.number_of_vertices\": 0, \"instance.symmetrical_type\": 0, \"model.generations\": 0, \"model.mutation_operator_probabilities.list.item\": 0, \"model.mutation_rate\": 0, \"model.name\": 0, \"model.population_size\": 0, \"model.selection_size\": 0, \"model.use_crossover\": 0, \"path_vertices.list.item\": 0, \"path_length\": 0, \"k_size\": 0}}","tags":null,"deletionVector":null,"baseRowId":null,"defaultRowCommitVersion":null,"clusteringProvider":null}}
{"commitInfo":{"timestamp":1749572665542,"operation":"CREATE TABLE","operationParameters":{"metadata":"{\"configuration\":{},\"createdTime\":1749572665542,\"description\":null,\"format\":{\"options\":{},\"provider\":\"parquet\"},\"id\":\"a10bfb70-0f65-4028-a5ab-d87525dceb52\",\"name\":null,\"partitionColumns\":[\"instance_name\",\"k_factor\",\"has_closed_cycle\",\"model_name\"],\"schemaString\":\"{\\\"type\\\":\\\"struct\\\",\\\"fields\\\":[{\\\"name\\\":\\\"experiment_id\\\",\\\"type\\\":\\\"string\\\",\\\"nullable\\\":true,\\\"metadata\\\":{}},{\\\"name\\\":\\\"experiment_name\\\",\\\"type\\\":\\\"string\\\",\\\"nullable\\\":true,\\\"metadata\\\":{}},{\\\"name\\\":\\\"instance_name\\\",\\\"type\\\":\\\"string\\\",\\\"nullable\\\":true,\\\"metadata\\\":{}},{\\\"name\\\":\\\"k_factor\\\",\\\"type\\\":\\\"double\\\",\\\"nullable\\\":true,\\\"metadata\\\":{}},{\\\"name\\\":\\\"repetitions\\\",\\\"type\\\":\\\"long\\\",\\\"nullable\\\":true,\\\"metadata\\\":{}},{\\\"name\\\":\\\"model_name\\\",\\\"type\\\":\\\"string\\\",\\\"nullable\\\":true,\\\"metadata\\\":{}},{\\\"name\\\":\\\"has_closed_cycle\\\",\\\"type\\\":\\\"boolean\\\",\\\"nullable\\\":true,\\\"metadata\\\":{}},{\\\"name\\\":\\\"session_id\\\",\\\"type\\\":\\\"string\\\",\\\"nullable\\\":true,\\\"metadata\\\":{}},{\\\"name\\\":\\\"instance\\\",\\\"type\\\":{\\\"type\\\":\\\"struct\\\",\\\"fields\\\":[{\\\"name\\\":\\\"name\\\",\\\"type\\\":\\\"string\\\",\\\"nullable\\\":true,\\\"metadata\\\":{}},{\\\"name\\\":\\\"number_of_edges\\\",\\\"type\\\":\\\"long\\\",\\\"nullable\\\":true,\\\"metadata\\\":{}},{\\\"name\\\":\\\"number_of_vertices\\\",\\\"type\\\":\\\"long\\\",\\\"nullable\\\":true,\\\"metadata\\\":{}},{\\\"name\\\":\\\"symmetrical_type\\\",\\\"type\\\":\\\"string\\\",\\\"nullable\\\":true,\\\"metadata\\\":{}}]},\\\"nullable\\\":true,\\\"metadata\\\":{}},{\\\"name\\\":\\\"model\\\",\\\"type\\\":{\\\"type\\\":\\\"struct\\\",\\\"fields\\\":[{\\\"name\\\":\\\"generations\\\",\\\"type\\\":\\\"long\\\",\\\"nullable\\\":true,\\\"metadata\\\":{}},{\\\"name\\\":\\\"mutation_operator_probabilities\\\",\\\"type\\\":{\\\"type\\\":\\\"array\\\",\\\"elementType\\\":\\\"double\\\",\\\"containsNull\\\":true},\\\"nullable\\\":true,\\\"metadata\\\":{}},{\\\"name\\\":\\\"mutation_rate\\\",\\\"type\\\":\\\"double\\\",\\\"nullable\\\":true,\\\"metadata\\\":{}},{\\\"name\\\":\\\"name\\\",\\\"type\\\":\\\"string\\\",\\\"nullable\\\":true,\\\"metadata\\\":{}},{\\\"name\\\":\\\"population_size\\\",\\\"type\\\":\\\"long\\\",\\\"nullable\\\":true,\\\"metadata\\\":{}},{\\\"name\\\":\\\"selection_size\\\",\\\"type\\\":\\\"long\\\",\\\"nullable\\\":true,\\\"metadata\\\":{}},{\\\"name\\\":\\\"use_crossover\\\",\\\"type\\\":\\\"boolean\\\",\\\"nullable\\\":true,\\\"metadata\\\":{}}]},\\\"nullable\\\":true,\\\"metadata\\\":{}},{\\\"name\\\":\\\"path_vertices\\\",\\\"type\\\":{\\\"type\\\":\\\"array\\\",\\\"elementType\\\":\\\"long\\\",\\\"containsNull\\\":true},\\\"nullable\\\":true,\\\"metadata\\\":{}},{\\\"name\\\":\\\"path_length\\\",\\\"type\\\":\\\"long\\\",\\\"nullable\\\":true,\\\"metadata\\\":{}},{\\\"name\\\":\\\"k_size\\\",\\\"type\\\":\\\"long\\\",\\\"nullable\\\":true,\\\"metadata\\\":{}}]}\"}","mode":"ErrorIfExists","protocol":"{\"minReaderVersion\":1,\"minWriterVersion\":2}","location":"file:///home/leo/projects/k-tsp-solver/results/hyperparameter_tuning__grouped_bayesian_search/2f541d89-4617-11f0-b9b3-631adf8121e0"},"clientVersion":"delta-rs.0.17.3"}}