{"protocol":{"minReaderVersion":1,"minWriterVersion":2}}
{"metaData":{"id":"ad378228-840a-490a-84dd-6cb79a0887a5","name":null,"description":null,"format":{"provider":"parquet","options":{}},"schemaString":"{\"type\":\"struct\",\"fields\":[{\"name\":\"experiment_id\",\"type\":\"string\",\"nullable\":true,\"metadata\":{}},{\"name\":\"experiment_name\",\"type\":\"string\",\"nullable\":true,\"metadata\":{}},{\"name\":\"instance_name\",\"type\":\"string\",\"nullable\":true,\"metadata\":{}},{\"name\":\"k_factor\",\"type\":\"double\",\"nullable\":true,\"metadata\":{}},{\"name\":\"repetitions\",\"type\":\"long\",\"nullable\":true,\"metadata\":{}},{\"name\":\"model_name\",\"type\":\"string\",\"nullable\":true,\"metadata\":{}},{\"name\":\"has_closed_cycle\",\"type\":\"boolean\",\"nullable\":true,\"metadata\":{}},{\"name\":\"session_id\",\"type\":\"string\",\"nullable\":true,\"metadata\":{}},{\"name\":\"instance\",\"type\":{\"type\":\"struct\",\"fields\":[{\"name\":\"name\",\"type\":\"string\",\"nullable\":true,\"metadata\":{}},{\"name\":\"number_of_edges\",\"type\":\"long\",\"nullable\":true,\"metadata\":{}},{\"name\":\"number_of_vertices\",\"type\":\"long\",\"nullable\":true,\"metadata\":{}},{\"name\":\"symmetrical_type\",\"type\":\"string\",\"nullable\":true,\"metadata\":{}}]},\"nullable\":true,\"metadata\":{}},{\"name\":\"model\",\"type\":{\"type\":\"struct\",\"fields\":[{\"name\":\"generations\",\"type\":\"long\",\"nullable\":true,\"metadata\":{}},{\"name\":\"mutation_operator_probabilities\",\"type\":{\"type\":\"array\",\"elementType\":\"double\",\"containsNull\":true},\"nullable\":true,\"metadata\":{}},{\"name\":\"mutation_rate\",\"type\":\"double\",\"nullable\":true,\"metadata\":{}},{\"name\":\"name\",\"type\":\"string\",\"nullable\":true,\"metadata\":{}},{\"name\":\"population_size\",\"type\":\"long\",\"nullable\":true,\"metadata\":{}},{\"name\":\"selection_size\",\"type\":\"long\",\"nullable\":true,\"metadata\":{}},{\"name\":\"use_crossover\",\"type\":\"boolean\",\"nullable\":true,\"metadata\":{}}]},\"nullable\":true,\"metadata\":{}},{\"name\":\"path_vertices\",\"type\":{\"type\":\"array\",\"elementType\":\"long\",\"containsNull\":true},\"nullable\":true,\"metadata\":{}},{\"name\":\"path_length\",\"type\":\"long\",\"nullable\":true,\"metadata\":{}},{\"name\":\"k_size\",\"type\":\"long\",\"nullable\":true,\"metadata\":{}}]}","partitionColumns":["instance_name","k_factor","has_closed_cycle","model_name"],"createdTime":1749173640571,"configuration":{}}}
{"add":{"path":"instance_name=ch130.tsp/k_factor=0.5/has_closed_cycle=true/model_name=GeneticAlgorithmNearestNeighborsEnsemble/0-050fe39e-bf0f-4f8e-bf7b-7eb1ad58ace3-0.parquet","partitionValues":{"has_closed_cycle":"true","model_name":"GeneticAlgorithmNearestNeighborsEnsemble","k_factor":"0.5","instance_name":"ch130.tsp"},"size":8950,"modificationTime":1749173640570,"dataChange":true,"stats":"{\"numRecords\": 10, \"minValues\": {\"experiment_id\": \"4e51d5d0-4276-11f0-b9ef-7cc25567a3b2\", \"experiment_name\": \"soa_replication\", \"repetitions\": 10, \"session_id\": \"4f47271a-4276-11f0-b9ef-7cc25567a3b2\", \"instance.name\": \"ch130.tsp\", \"instance.number_of_edges\": 8515, \"instance.number_of_vertices\": 130, \"instance.symmetrical_type\": \"TSP\", \"model.generations\": 100, \"model.mutation_operator_probabilities.list.item\": -0.0, \"model.mutation_rate\": 0.01, \"model.name\": \"GeneticAlgorithmNearestNeighborsEnsemble\", \"model.population_size\": 100, \"model.selection_size\": 10, \"model.use_crossover\": false, \"path_vertices.list.item\": 1, \"path_length\": 2775, \"k_size\": 65}, \"maxValues\": {\"experiment_id\": \"4e51d5d0-4276-11f0-b9ef-7cc25567a3b2\", \"experiment_name\": \"soa_replication\", \"repetitions\": 10, \"session_id\": \"52755902-4276-11f0-b9ef-7cc25567a3b2\", \"instance.name\": \"ch130.tsp\", \"instance.number_of_edges\": 8515, \"instance.number_of_vertices\": 130, \"instance.symmetrical_type\": \"TSP\", \"model.generations\": 100, \"model.mutation_operator_probabilities.list.item\": 0.3333333333333333, \"model.mutation_rate\": 0.01, \"model.name\": \"GeneticAlgorithmNearestNeighborsEnsemble\", \"model.population_size\": 100, \"model.selection_size\": 10, \"model.use_crossover\": false, \"path_vertices.list.item\": 130, \"path_length\": 2802, \"k_size\": 65}, \"nullCount\": {\"experiment_id\": 0, \"experiment_name\": 0, \"repetitions\": 0, \"session_id\": 0, \"instance.name\": 0, \"instance.number_of_edges\": 0, \"instance.number_of_vertices\": 0, \"instance.symmetrical_type\": 0, \"model.generations\": 9, \"model.mutation_operator_probabilities.list.item\": 9, \"model.mutation_rate\": 9, \"model.name\": 0, \"model.population_size\": 9, \"model.selection_size\": 9, \"model.use_crossover\": 9, \"path_vertices.list.item\": 0, \"path_length\": 0, \"k_size\": 0}}","tags":null,"deletionVector":null,"baseRowId":null,"defaultRowCommitVersion":null,"clusteringProvider":null}}
{"commitInfo":{"timestamp":1749173640571,"operation":"CREATE TABLE","operationParameters":{"mode":"ErrorIfExists","metadata":"{\"configuration\":{},\"createdTime\":1749173640571,\"description\":null,\"format\":{\"options\":{},\"provider\":\"parquet\"},\"id\":\"ad378228-840a-490a-84dd-6cb79a0887a5\",\"name\":null,\"partitionColumns\":[\"instance_name\",\"k_factor\",\"has_closed_cycle\",\"model_name\"],\"schemaString\":\"{\\\"type\\\":\\\"struct\\\",\\\"fields\\\":[{\\\"name\\\":\\\"experiment_id\\\",\\\"type\\\":\\\"string\\\",\\\"nullable\\\":true,\\\"metadata\\\":{}},{\\\"name\\\":\\\"experiment_name\\\",\\\"type\\\":\\\"string\\\",\\\"nullable\\\":true,\\\"metadata\\\":{}},{\\\"name\\\":\\\"instance_name\\\",\\\"type\\\":\\\"string\\\",\\\"nullable\\\":true,\\\"metadata\\\":{}},{\\\"name\\\":\\\"k_factor\\\",\\\"type\\\":\\\"double\\\",\\\"nullable\\\":true,\\\"metadata\\\":{}},{\\\"name\\\":\\\"repetitions\\\",\\\"type\\\":\\\"long\\\",\\\"nullable\\\":true,\\\"metadata\\\":{}},{\\\"name\\\":\\\"model_name\\\",\\\"type\\\":\\\"string\\\",\\\"nullable\\\":true,\\\"metadata\\\":{}},{\\\"name\\\":\\\"has_closed_cycle\\\",\\\"type\\\":\\\"boolean\\\",\\\"nullable\\\":true,\\\"metadata\\\":{}},{\\\"name\\\":\\\"session_id\\\",\\\"type\\\":\\\"string\\\",\\\"nullable\\\":true,\\\"metadata\\\":{}},{\\\"name\\\":\\\"instance\\\",\\\"type\\\":{\\\"type\\\":\\\"struct\\\",\\\"fields\\\":[{\\\"name\\\":\\\"name\\\",\\\"type\\\":\\\"string\\\",\\\"nullable\\\":true,\\\"metadata\\\":{}},{\\\"name\\\":\\\"number_of_edges\\\",\\\"type\\\":\\\"long\\\",\\\"nullable\\\":true,\\\"metadata\\\":{}},{\\\"name\\\":\\\"number_of_vertices\\\",\\\"type\\\":\\\"long\\\",\\\"nullable\\\":true,\\\"metadata\\\":{}},{\\\"name\\\":\\\"symmetrical_type\\\",\\\"type\\\":\\\"string\\\",\\\"nullable\\\":true,\\\"metadata\\\":{}}]},\\\"nullable\\\":true,\\\"metadata\\\":{}},{\\\"name\\\":\\\"model\\\",\\\"type\\\":{\\\"type\\\":\\\"struct\\\",\\\"fields\\\":[{\\\"name\\\":\\\"generations\\\",\\\"type\\\":\\\"long\\\",\\\"nullable\\\":true,\\\"metadata\\\":{}},{\\\"name\\\":\\\"mutation_operator_probabilities\\\",\\\"type\\\":{\\\"type\\\":\\\"array\\\",\\\"elementType\\\":\\\"double\\\",\\\"containsNull\\\":true},\\\"nullable\\\":true,\\\"metadata\\\":{}},{\\\"name\\\":\\\"mutation_rate\\\",\\\"type\\\":\\\"double\\\",\\\"nullable\\\":true,\\\"metadata\\\":{}},{\\\"name\\\":\\\"name\\\",\\\"type\\\":\\\"string\\\",\\\"nullable\\\":true,\\\"metadata\\\":{}},{\\\"name\\\":\\\"population_size\\\",\\\"type\\\":\\\"long\\\",\\\"nullable\\\":true,\\\"metadata\\\":{}},{\\\"name\\\":\\\"selection_size\\\",\\\"type\\\":\\\"long\\\",\\\"nullable\\\":true,\\\"metadata\\\":{}},{\\\"name\\\":\\\"use_crossover\\\",\\\"type\\\":\\\"boolean\\\",\\\"nullable\\\":true,\\\"metadata\\\":{}}]},\\\"nullable\\\":true,\\\"metadata\\\":{}},{\\\"name\\\":\\\"path_vertices\\\",\\\"type\\\":{\\\"type\\\":\\\"array\\\",\\\"elementType\\\":\\\"long\\\",\\\"containsNull\\\":true},\\\"nullable\\\":true,\\\"metadata\\\":{}},{\\\"name\\\":\\\"path_length\\\",\\\"type\\\":\\\"long\\\",\\\"nullable\\\":true,\\\"metadata\\\":{}},{\\\"name\\\":\\\"k_size\\\",\\\"type\\\":\\\"long\\\",\\\"nullable\\\":true,\\\"metadata\\\":{}}]}\"}","protocol":"{\"minReaderVersion\":1,\"minWriterVersion\":2}","location":"file:///home/leonichel/k-tsp-solver/results/soa_replication/4e51d5d0-4276-11f0-b9ef-7cc25567a3b2"},"clientVersion":"delta-rs.0.17.3"}}