{"add":{"path":"instance_name=ft70.atsp/k_factor=0.5/has_closed_cycle=true/model_name=NearestNeighbors/1413-7c85b9e1-6016-4999-91f6-75a1a5705dbb-0.parquet","partitionValues":{"k_factor":"0.5","model_name":"NearestNeighbors","instance_name":"ft70.atsp","has_closed_cycle":"true"},"size":4507,"modificationTime":1715587275469,"dataChange":true,"stats":"{\"numRecords\": 1, \"minValues\": {\"session_id\": \"f8a6a3be-10fe-11ef-a05f-a5df095bf5b7\", \"instance_number_of_vertices\": 70, \"instance_number_of_edges\": 4900, \"instance_symmetrical_type\": \"ATSP\", \"model\": \"{'name': 'NearestNeighbors'}\", \"path_vertices.list.item\": 3, \"path_length\": 20211, \"k_size\": 35, \"experiment_id\": \"f8a6a3bd-10fe-11ef-a05f-a5df095bf5b7\"}, \"maxValues\": {\"session_id\": \"f8a6a3be-10fe-11ef-a05f-a5df095bf5b7\", \"instance_number_of_vertices\": 70, \"instance_number_of_edges\": 4900, \"instance_symmetrical_type\": \"ATSP\", \"model\": \"{'name': 'NearestNeighbors'}\", \"path_vertices.list.item\": 69, \"path_length\": 20211, \"k_size\": 35, \"experiment_id\": \"f8a6a3bd-10fe-11ef-a05f-a5df095bf5b7\"}, \"nullCount\": {\"session_id\": 0, \"instance_number_of_vertices\": 0, \"instance_number_of_edges\": 0, \"instance_symmetrical_type\": 0, \"model\": 0, \"path_vertices.list.item\": 0, \"path_length\": 0, \"k_size\": 0, \"experiment_id\": 0}}","tags":null,"deletionVector":null,"baseRowId":null,"defaultRowCommitVersion":null,"clusteringProvider":null}}
{"commitInfo":{"timestamp":1715587275470,"operation":"WRITE","operationParameters":{"partitionBy":"[\"instance_name\",\"k_factor\",\"has_closed_cycle\",\"model_name\"]","mode":"Append"},"clientVersion":"delta-rs.0.17.3"}}