{"add":{"path":"instance_name=gr229.tsp/k_factor=0.5/has_closed_cycle=false/model_name=GeneticAlgorithm/511-66ea7952-94cf-4795-9d87-e2d8dcaf7c7b-0.parquet","partitionValues":{"model_name":"GeneticAlgorithm","instance_name":"gr229.tsp","k_factor":"0.5","has_closed_cycle":"false"},"size":7266,"modificationTime":1715511143678,"dataChange":true,"stats":"{\"numRecords\": 10, \"minValues\": {\"session_id\": \"82f77a58-104d-11ef-a05f-a5df095bf5b7\", \"instance_number_of_vertices\": 229, \"instance_number_of_edges\": 26335, \"instance_symmetrical_type\": \"TSP\", \"model\": \"{'name': 'GeneticAlgorithm', 'population_size': 100, 'generations': 100, 'mutation_rate': 1.0, 'selection_size': 10}\", \"path_vertices.list.item\": 1, \"path_length\": 424440, \"k_size\": 114, \"experiment_id\": \"7c27dc1b-104d-11ef-a05f-a5df095bf5b7\"}, \"maxValues\": {\"session_id\": \"b6bfb206-104d-11ef-a05f-a5df095bf5b7\", \"instance_number_of_vertices\": 229, \"instance_number_of_edges\": 26335, \"instance_symmetrical_type\": \"TSP\", \"model\": \"{'name': 'GeneticAlgorithm', 'population_size': 100, 'generations': 100, 'mutation_rate': 1.0204081632653061, 'selection_size': 10}\", \"path_vertices.list.item\": 227, \"path_length\": 543097, \"k_size\": 114, \"experiment_id\": \"7c27dc1b-104d-11ef-a05f-a5df095bf5b7\"}, \"nullCount\": {\"session_id\": 0, \"instance_number_of_vertices\": 0, \"instance_number_of_edges\": 0, \"instance_symmetrical_type\": 0, \"model\": 0, \"path_vertices.list.item\": 0, \"path_length\": 0, \"k_size\": 0, \"experiment_id\": 0}}","tags":null,"deletionVector":null,"baseRowId":null,"defaultRowCommitVersion":null,"clusteringProvider":null}}
{"commitInfo":{"timestamp":1715511143679,"operation":"WRITE","operationParameters":{"partitionBy":"[\"instance_name\",\"k_factor\",\"has_closed_cycle\",\"model_name\"]","mode":"Append"},"clientVersion":"delta-rs.0.17.3"}}