{"add":{"path":"instance_name=ftv33.atsp/k_factor=0.75/has_closed_cycle=true/model_name=NearestNeighbors/1437-a9c0226d-183f-4328-ba25-6c3e3ca249f5-0.parquet","partitionValues":{"instance_name":"ftv33.atsp","has_closed_cycle":"true","k_factor":"0.75","model_name":"NearestNeighbors"},"size":4456,"modificationTime":1716682868029,"dataChange":true,"stats":"{\"numRecords\": 1, \"minValues\": {\"session_id\": \"d86d0fa8-1af5-11ef-b3a9-3b6e94433e0b\", \"instance_number_of_vertices\": 34, \"instance_number_of_edges\": 1156, \"instance_symmetrical_type\": \"ATSP\", \"model\": \"{'name': 'NearestNeighbors'}\", \"path_vertices.list.item\": 0, \"path_length\": 925, \"k_size\": 25, \"experiment_id\": \"d86d0fa7-1af5-11ef-b3a9-3b6e94433e0b\"}, \"maxValues\": {\"session_id\": \"d86d0fa8-1af5-11ef-b3a9-3b6e94433e0b\", \"instance_number_of_vertices\": 34, \"instance_number_of_edges\": 1156, \"instance_symmetrical_type\": \"ATSP\", \"model\": \"{'name': 'NearestNeighbors'}\", \"path_vertices.list.item\": 32, \"path_length\": 925, \"k_size\": 25, \"experiment_id\": \"d86d0fa7-1af5-11ef-b3a9-3b6e94433e0b\"}, \"nullCount\": {\"session_id\": 0, \"instance_number_of_vertices\": 0, \"instance_number_of_edges\": 0, \"instance_symmetrical_type\": 0, \"model\": 0, \"path_vertices.list.item\": 0, \"path_length\": 0, \"k_size\": 0, \"experiment_id\": 0}}","tags":null,"deletionVector":null,"baseRowId":null,"defaultRowCommitVersion":null,"clusteringProvider":null}}
{"commitInfo":{"timestamp":1716682868029,"operation":"WRITE","operationParameters":{"mode":"Append","partitionBy":"[\"instance_name\",\"k_factor\",\"has_closed_cycle\",\"model_name\"]"},"clientVersion":"delta-rs.0.17.3"}}