{"add":{"path":"instance_name=pr264.tsp/k_factor=0.75/has_closed_cycle=false/model_name=Ensemble/1004-03455a3d-dc98-4abc-8518-0a2855aca1d7-0.parquet","partitionValues":{"model_name":"Ensemble","instance_name":"pr264.tsp","has_closed_cycle":"false","k_factor":"0.75"},"size":5558,"modificationTime":1716647855816,"dataChange":true,"stats":"{\"numRecords\": 10, \"minValues\": {\"session_id\": \"33c9f918-1aa4-11ef-b3a9-3b6e94433e0b\", \"instance_number_of_vertices\": 264, \"instance_number_of_edges\": 34980, \"instance_symmetrical_type\": \"TSP\", \"model\": \"{'name': 'NearestNeighbors'}\", \"path_vertices.list.item\": 1, \"path_length\": 33665, \"k_size\": 198, \"experiment_id\": \"2e2761ef-1aa4-11ef-b3a9-3b6e94433e0b\"}, \"maxValues\": {\"session_id\": \"53f07e06-1aa4-11ef-b3a9-3b6e94433e0b\", \"instance_number_of_vertices\": 264, \"instance_number_of_edges\": 34980, \"instance_symmetrical_type\": \"TSP\", \"model\": \"{'name': 'NearestNeighbors'}\", \"path_vertices.list.item\": 252, \"path_length\": 33665, \"k_size\": 198, \"experiment_id\": \"2e2761ef-1aa4-11ef-b3a9-3b6e94433e0b\"}, \"nullCount\": {\"session_id\": 0, \"instance_number_of_vertices\": 0, \"instance_number_of_edges\": 0, \"instance_symmetrical_type\": 0, \"model\": 0, \"path_vertices.list.item\": 0, \"path_length\": 0, \"k_size\": 0, \"experiment_id\": 0}}","tags":null,"deletionVector":null,"baseRowId":null,"defaultRowCommitVersion":null,"clusteringProvider":null}}
{"commitInfo":{"timestamp":1716647855817,"operation":"WRITE","operationParameters":{"mode":"Append","partitionBy":"[\"instance_name\",\"k_factor\",\"has_closed_cycle\",\"model_name\"]"},"clientVersion":"delta-rs.0.17.3"}}