{"add":{"path":"instance_name=u574.tsp/k_factor=0.75/has_closed_cycle=true/model_name=Ensemble/1313-9409d19f-74e7-4bab-8538-e3885436407a-0.parquet","partitionValues":{"instance_name":"u574.tsp","model_name":"Ensemble","k_factor":"0.75","has_closed_cycle":"true"},"size":11057,"modificationTime":1716676245060,"dataChange":true,"stats":"{\"numRecords\": 10, \"minValues\": {\"session_id\": \"138e6f7a-1ae6-11ef-b3a9-3b6e94433e0b\", \"instance_number_of_vertices\": 574, \"instance_number_of_edges\": 165025, \"instance_symmetrical_type\": \"TSP\", \"model\": \"{'name': 'NearestNeighbors'}\", \"path_vertices.list.item\": 14, \"path_length\": 27144, \"k_size\": 430, \"experiment_id\": \"ff6e378d-1ae5-11ef-b3a9-3b6e94433e0b\"}, \"maxValues\": {\"session_id\": \"6d44f16a-1ae6-11ef-b3a9-3b6e94433e0b\", \"instance_number_of_vertices\": 574, \"instance_number_of_edges\": 165025, \"instance_symmetrical_type\": \"TSP\", \"model\": \"{'name': 'NearestNeighbors'}\", \"path_vertices.list.item\": 545, \"path_length\": 27165, \"k_size\": 430, \"experiment_id\": \"ff6e378d-1ae5-11ef-b3a9-3b6e94433e0b\"}, \"nullCount\": {\"session_id\": 0, \"instance_number_of_vertices\": 0, \"instance_number_of_edges\": 0, \"instance_symmetrical_type\": 0, \"model\": 0, \"path_vertices.list.item\": 0, \"path_length\": 0, \"k_size\": 0, \"experiment_id\": 0}}","tags":null,"deletionVector":null,"baseRowId":null,"defaultRowCommitVersion":null,"clusteringProvider":null}}
{"commitInfo":{"timestamp":1716676245060,"operation":"WRITE","operationParameters":{"mode":"Append","partitionBy":"[\"instance_name\",\"k_factor\",\"has_closed_cycle\",\"model_name\"]"},"clientVersion":"delta-rs.0.17.3"}}