{"add":{"path":"instance_name=gr120.tsp/k_factor=0.5/has_closed_cycle=false/model_name=GeneticAlgorithm/421-c3e85a1c-73e8-4f6b-9d06-28fef2d621c7-0.parquet","partitionValues":{"has_closed_cycle":"false","k_factor":"0.5","model_name":"GeneticAlgorithm","instance_name":"gr120.tsp"},"size":6195,"modificationTime":1715509342751,"dataChange":true,"stats":"{\"numRecords\": 10, \"minValues\": {\"session_id\": \"743b2c02-1049-11ef-a05f-a5df095bf5b7\", \"instance_number_of_vertices\": 120, \"instance_number_of_edges\": 7260, \"instance_symmetrical_type\": \"TSP\", \"model\": \"{'name': 'GeneticAlgorithm', 'population_size': 100, 'generations': 100, 'mutation_rate': 1.0, 'selection_size': 10}\", \"path_vertices.list.item\": 1, \"path_length\": 14514, \"k_size\": 60, \"experiment_id\": \"72bbd8ed-1049-11ef-a05f-a5df095bf5b7\"}, \"maxValues\": {\"session_id\": \"854da1dc-1049-11ef-a05f-a5df095bf5b7\", \"instance_number_of_vertices\": 120, \"instance_number_of_edges\": 7260, \"instance_symmetrical_type\": \"TSP\", \"model\": \"{'name': 'GeneticAlgorithm', 'population_size': 100, 'generations': 100, 'mutation_rate': 1.0204081632653061, 'selection_size': 10}\", \"path_vertices.list.item\": 120, \"path_length\": 17821, \"k_size\": 60, \"experiment_id\": \"72bbd8ed-1049-11ef-a05f-a5df095bf5b7\"}, \"nullCount\": {\"session_id\": 0, \"instance_number_of_vertices\": 0, \"instance_number_of_edges\": 0, \"instance_symmetrical_type\": 0, \"model\": 0, \"path_vertices.list.item\": 0, \"path_length\": 0, \"k_size\": 0, \"experiment_id\": 0}}","tags":null,"deletionVector":null,"baseRowId":null,"defaultRowCommitVersion":null,"clusteringProvider":null}}
{"commitInfo":{"timestamp":1715509342751,"operation":"WRITE","operationParameters":{"partitionBy":"[\"instance_name\",\"k_factor\",\"has_closed_cycle\",\"model_name\"]","mode":"Append"},"clientVersion":"delta-rs.0.17.3"}}