{"add":{"path":"instance_name=rbg403.atsp/k_factor=0.75/has_closed_cycle=true/model_name=GeneticAlgorithm/1672-11f8fafc-264a-466b-ade7-bc6b30e5f57d-0.parquet","partitionValues":{"has_closed_cycle":"true","instance_name":"rbg403.atsp","k_factor":"0.75","model_name":"GeneticAlgorithm"},"size":10250,"modificationTime":1715598437320,"dataChange":true,"stats":"{\"numRecords\": 10, \"minValues\": {\"session_id\": \"1a842806-1118-11ef-a05f-a5df095bf5b7\", \"instance_number_of_vertices\": 403, \"instance_number_of_edges\": 162409, \"instance_symmetrical_type\": \"ATSP\", \"model\": \"{'name': 'GeneticAlgorithm', 'population_size': 100, 'generations': 100, 'mutation_rate': 1.0, 'selection_size': 10}\", \"path_vertices.list.item\": 0, \"path_length\": 5114, \"k_size\": 302, \"experiment_id\": \"b9eba2d3-1117-11ef-a05f-a5df095bf5b7\"}, \"maxValues\": {\"session_id\": \"fa731a5e-1117-11ef-a05f-a5df095bf5b7\", \"instance_number_of_vertices\": 403, \"instance_number_of_edges\": 162409, \"instance_symmetrical_type\": \"ATSP\", \"model\": \"{'name': 'GeneticAlgorithm', 'population_size': 100, 'generations': 100, 'mutation_rate': 1.0204081632653061, 'selection_size': 10}\", \"path_vertices.list.item\": 402, \"path_length\": 5322, \"k_size\": 302, \"experiment_id\": \"b9eba2d3-1117-11ef-a05f-a5df095bf5b7\"}, \"nullCount\": {\"session_id\": 0, \"instance_number_of_vertices\": 0, \"instance_number_of_edges\": 0, \"instance_symmetrical_type\": 0, \"model\": 0, \"path_vertices.list.item\": 0, \"path_length\": 0, \"k_size\": 0, \"experiment_id\": 0}}","tags":null,"deletionVector":null,"baseRowId":null,"defaultRowCommitVersion":null,"clusteringProvider":null}}
{"commitInfo":{"timestamp":1715598437321,"operation":"WRITE","operationParameters":{"mode":"Append","partitionBy":"[\"instance_name\",\"k_factor\",\"has_closed_cycle\",\"model_name\"]"},"clientVersion":"delta-rs.0.17.3"}}