{"protocol":{"minReaderVersion":1,"minWriterVersion":2}}
{"metaData":{"id":"fbd65985-b98a-47de-a6c7-750c2a53e5fd","name":null,"description":null,"format":{"provider":"parquet","options":{}},"schemaString":"{\"type\":\"struct\",\"fields\":[{\"name\":\"experiment_id\",\"type\":\"string\",\"nullable\":true,\"metadata\":{}},{\"name\":\"experiment_name\",\"type\":\"string\",\"nullable\":true,\"metadata\":{}},{\"name\":\"instance_name\",\"type\":\"string\",\"nullable\":true,\"metadata\":{}},{\"name\":\"k_factor\",\"type\":\"double\",\"nullable\":true,\"metadata\":{}},{\"name\":\"repetitions\",\"type\":\"long\",\"nullable\":true,\"metadata\":{}},{\"name\":\"model_name\",\"type\":\"string\",\"nullable\":true,\"metadata\":{}},{\"name\":\"has_closed_cycle\",\"type\":\"boolean\",\"nullable\":true,\"metadata\":{}},{\"name\":\"session_id\",\"type\":\"string\",\"nullable\":true,\"metadata\":{}},{\"name\":\"instance\",\"type\":{\"type\":\"struct\",\"fields\":[{\"name\":\"name\",\"type\":\"string\",\"nullable\":true,\"metadata\":{}},{\"name\":\"number_of_edges\",\"type\":\"long\",\"nullable\":true,\"metadata\":{}},{\"name\":\"number_of_vertices\",\"type\":\"long\",\"nullable\":true,\"metadata\":{}},{\"name\":\"symmetrical_type\",\"type\":\"string\",\"nullable\":true,\"metadata\":{}}]},\"nullable\":true,\"metadata\":{}},{\"name\":\"model\",\"type\":{\"type\":\"struct\",\"fields\":[{\"name\":\"name\",\"type\":\"string\",\"nullable\":true,\"metadata\":{}}]},\"nullable\":true,\"metadata\":{}},{\"name\":\"path_vertices\",\"type\":{\"type\":\"array\",\"elementType\":\"long\",\"containsNull\":true},\"nullable\":true,\"metadata\":{}},{\"name\":\"path_length\",\"type\":\"long\",\"nullable\":true,\"metadata\":{}},{\"name\":\"k_size\",\"type\":\"long\",\"nullable\":true,\"metadata\":{}}]}","partitionColumns":["instance_name","k_factor","has_closed_cycle","model_name"],"createdTime":1749176782097,"configuration":{}}}
{"add":{"path":"instance_name=rat99.tsp/k_factor=0.25/has_closed_cycle=true/model_name=GeneticAlgorithmNearestNeighborsEnsemble/0-761ee10f-0ed2-4b31-addb-0cbb1d273ae7-0.parquet","partitionValues":{"instance_name":"rat99.tsp","has_closed_cycle":"true","model_name":"GeneticAlgorithmNearestNeighborsEnsemble","k_factor":"0.25"},"size":6290,"modificationTime":1749176782096,"dataChange":true,"stats":"{\"numRecords\": 30, \"minValues\": {\"experiment_id\": \"9ee17a8a-427d-11f0-9e13-7cc25567a3b2\", \"experiment_name\": \"change__ordered_crossover\", \"repetitions\": 30, \"session_id\": \"9f8243c0-427d-11f0-9e13-7cc25567a3b2\", \"instance.name\": \"rat99.tsp\", \"instance.number_of_edges\": 4950, \"instance.number_of_vertices\": 99, \"instance.symmetrical_type\": \"TSP\", \"model.name\": \"GeneticAlgorithmNearestNeighborsEnsemble\", \"path_vertices.list.item\": 32, \"path_length\": 273, \"k_size\": 24}, \"maxValues\": {\"experiment_id\": \"9ee17a8a-427d-11f0-9e13-7cc25567a3b2\", \"experiment_name\": \"change__ordered_crossover\", \"repetitions\": 30, \"session_id\": \"a2f6230a-427d-11f0-9e13-7cc25567a3b2\", \"instance.name\": \"rat99.tsp\", \"instance.number_of_edges\": 4950, \"instance.number_of_vertices\": 99, \"instance.symmetrical_type\": \"TSP\", \"model.name\": \"GeneticAlgorithmNearestNeighborsEnsemble\", \"path_vertices.list.item\": 60, \"path_length\": 273, \"k_size\": 24}, \"nullCount\": {\"experiment_id\": 0, \"experiment_name\": 0, \"repetitions\": 0, \"session_id\": 0, \"instance.name\": 0, \"instance.number_of_edges\": 0, \"instance.number_of_vertices\": 0, \"instance.symmetrical_type\": 0, \"model.name\": 0, \"path_vertices.list.item\": 0, \"path_length\": 0, \"k_size\": 0}}","tags":null,"deletionVector":null,"baseRowId":null,"defaultRowCommitVersion":null,"clusteringProvider":null}}
{"commitInfo":{"timestamp":1749176782097,"operation":"CREATE TABLE","operationParameters":{"mode":"ErrorIfExists","protocol":"{\"minReaderVersion\":1,\"minWriterVersion\":2}","location":"file:///home/leonichel/k-tsp-solver/results/change__ordered_crossover/9ee17a8a-427d-11f0-9e13-7cc25567a3b2","metadata":"{\"configuration\":{},\"createdTime\":1749176782097,\"description\":null,\"format\":{\"options\":{},\"provider\":\"parquet\"},\"id\":\"fbd65985-b98a-47de-a6c7-750c2a53e5fd\",\"name\":null,\"partitionColumns\":[\"instance_name\",\"k_factor\",\"has_closed_cycle\",\"model_name\"],\"schemaString\":\"{\\\"type\\\":\\\"struct\\\",\\\"fields\\\":[{\\\"name\\\":\\\"experiment_id\\\",\\\"type\\\":\\\"string\\\",\\\"nullable\\\":true,\\\"metadata\\\":{}},{\\\"name\\\":\\\"experiment_name\\\",\\\"type\\\":\\\"string\\\",\\\"nullable\\\":true,\\\"metadata\\\":{}},{\\\"name\\\":\\\"instance_name\\\",\\\"type\\\":\\\"string\\\",\\\"nullable\\\":true,\\\"metadata\\\":{}},{\\\"name\\\":\\\"k_factor\\\",\\\"type\\\":\\\"double\\\",\\\"nullable\\\":true,\\\"metadata\\\":{}},{\\\"name\\\":\\\"repetitions\\\",\\\"type\\\":\\\"long\\\",\\\"nullable\\\":true,\\\"metadata\\\":{}},{\\\"name\\\":\\\"model_name\\\",\\\"type\\\":\\\"string\\\",\\\"nullable\\\":true,\\\"metadata\\\":{}},{\\\"name\\\":\\\"has_closed_cycle\\\",\\\"type\\\":\\\"boolean\\\",\\\"nullable\\\":true,\\\"metadata\\\":{}},{\\\"name\\\":\\\"session_id\\\",\\\"type\\\":\\\"string\\\",\\\"nullable\\\":true,\\\"metadata\\\":{}},{\\\"name\\\":\\\"instance\\\",\\\"type\\\":{\\\"type\\\":\\\"struct\\\",\\\"fields\\\":[{\\\"name\\\":\\\"name\\\",\\\"type\\\":\\\"string\\\",\\\"nullable\\\":true,\\\"metadata\\\":{}},{\\\"name\\\":\\\"number_of_edges\\\",\\\"type\\\":\\\"long\\\",\\\"nullable\\\":true,\\\"metadata\\\":{}},{\\\"name\\\":\\\"number_of_vertices\\\",\\\"type\\\":\\\"long\\\",\\\"nullable\\\":true,\\\"metadata\\\":{}},{\\\"name\\\":\\\"symmetrical_type\\\",\\\"type\\\":\\\"string\\\",\\\"nullable\\\":true,\\\"metadata\\\":{}}]},\\\"nullable\\\":true,\\\"metadata\\\":{}},{\\\"name\\\":\\\"model\\\",\\\"type\\\":{\\\"type\\\":\\\"struct\\\",\\\"fields\\\":[{\\\"name\\\":\\\"name\\\",\\\"type\\\":\\\"string\\\",\\\"nullable\\\":true,\\\"metadata\\\":{}}]},\\\"nullable\\\":true,\\\"metadata\\\":{}},{\\\"name\\\":\\\"path_vertices\\\",\\\"type\\\":{\\\"type\\\":\\\"array\\\",\\\"elementType\\\":\\\"long\\\",\\\"containsNull\\\":true},\\\"nullable\\\":true,\\\"metadata\\\":{}},{\\\"name\\\":\\\"path_length\\\",\\\"type\\\":\\\"long\\\",\\\"nullable\\\":true,\\\"metadata\\\":{}},{\\\"name\\\":\\\"k_size\\\",\\\"type\\\":\\\"long\\\",\\\"nullable\\\":true,\\\"metadata\\\":{}}]}\"}"},"clientVersion":"delta-rs.0.17.3"}}