{"protocol":{"minReaderVersion":1,"minWriterVersion":2}}
{"metaData":{"id":"1c06773c-b41f-4189-ace4-00d1beb1370c","name":null,"description":null,"format":{"provider":"parquet","options":{}},"schemaString":"{\"type\":\"struct\",\"fields\":[{\"name\":\"experiment_id\",\"type\":\"string\",\"nullable\":true,\"metadata\":{}},{\"name\":\"experiment_name\",\"type\":\"string\",\"nullable\":true,\"metadata\":{}},{\"name\":\"instance_name\",\"type\":\"string\",\"nullable\":true,\"metadata\":{}},{\"name\":\"k_factor\",\"type\":\"double\",\"nullable\":true,\"metadata\":{}},{\"name\":\"repetitions\",\"type\":\"long\",\"nullable\":true,\"metadata\":{}},{\"name\":\"model_name\",\"type\":\"string\",\"nullable\":true,\"metadata\":{}},{\"name\":\"has_closed_cycle\",\"type\":\"boolean\",\"nullable\":true,\"metadata\":{}},{\"name\":\"session_id\",\"type\":\"string\",\"nullable\":true,\"metadata\":{}},{\"name\":\"instance\",\"type\":{\"type\":\"struct\",\"fields\":[{\"name\":\"name\",\"type\":\"string\",\"nullable\":true,\"metadata\":{}},{\"name\":\"number_of_edges\",\"type\":\"long\",\"nullable\":true,\"metadata\":{}},{\"name\":\"number_of_vertices\",\"type\":\"long\",\"nullable\":true,\"metadata\":{}},{\"name\":\"symmetrical_type\",\"type\":\"string\",\"nullable\":true,\"metadata\":{}}]},\"nullable\":true,\"metadata\":{}},{\"name\":\"model\",\"type\":{\"type\":\"struct\",\"fields\":[{\"name\":\"name\",\"type\":\"string\",\"nullable\":true,\"metadata\":{}}]},\"nullable\":true,\"metadata\":{}},{\"name\":\"path_vertices\",\"type\":{\"type\":\"array\",\"elementType\":\"long\",\"containsNull\":true},\"nullable\":true,\"metadata\":{}},{\"name\":\"path_length\",\"type\":\"long\",\"nullable\":true,\"metadata\":{}},{\"name\":\"k_size\",\"type\":\"long\",\"nullable\":true,\"metadata\":{}}]}","partitionColumns":["instance_name","k_factor","has_closed_cycle","model_name"],"createdTime":1749173661866,"configuration":{}}}
{"add":{"path":"instance_name=pr264.tsp/k_factor=0.25/has_closed_cycle=false/model_name=GeneticAlgorithmNearestNeighborsEnsemble/0-9ebc8d30-d270-41f3-a3d9-6a0c49acd0e7-0.parquet","partitionValues":{"k_factor":"0.25","has_closed_cycle":"false","instance_name":"pr264.tsp","model_name":"GeneticAlgorithmNearestNeighborsEnsemble"},"size":6298,"modificationTime":1749173661862,"dataChange":true,"stats":"{\"numRecords\": 10, \"minValues\": {\"experiment_id\": \"59da1476-4276-11f0-a63e-7cc25567a3b2\", \"experiment_name\": \"soa_replication\", \"repetitions\": 10, \"session_id\": \"5b4c2a6a-4276-11f0-a63e-7cc25567a3b2\", \"instance.name\": \"pr264.tsp\", \"instance.number_of_edges\": 34980, \"instance.number_of_vertices\": 264, \"instance.symmetrical_type\": \"TSP\", \"model.name\": \"GeneticAlgorithmNearestNeighborsEnsemble\", \"path_vertices.list.item\": 16, \"path_length\": 7700, \"k_size\": 66}, \"maxValues\": {\"experiment_id\": \"59da1476-4276-11f0-a63e-7cc25567a3b2\", \"experiment_name\": \"soa_replication\", \"repetitions\": 10, \"session_id\": \"5f274bc4-4276-11f0-a63e-7cc25567a3b2\", \"instance.name\": \"pr264.tsp\", \"instance.number_of_edges\": 34980, \"instance.number_of_vertices\": 264, \"instance.symmetrical_type\": \"TSP\", \"model.name\": \"GeneticAlgorithmNearestNeighborsEnsemble\", \"path_vertices.list.item\": 121, \"path_length\": 7700, \"k_size\": 66}, \"nullCount\": {\"experiment_id\": 0, \"experiment_name\": 0, \"repetitions\": 0, \"session_id\": 0, \"instance.name\": 0, \"instance.number_of_edges\": 0, \"instance.number_of_vertices\": 0, \"instance.symmetrical_type\": 0, \"model.name\": 0, \"path_vertices.list.item\": 0, \"path_length\": 0, \"k_size\": 0}}","tags":null,"deletionVector":null,"baseRowId":null,"defaultRowCommitVersion":null,"clusteringProvider":null}}
{"commitInfo":{"timestamp":1749173661866,"operation":"CREATE TABLE","operationParameters":{"metadata":"{\"configuration\":{},\"createdTime\":1749173661866,\"description\":null,\"format\":{\"options\":{},\"provider\":\"parquet\"},\"id\":\"1c06773c-b41f-4189-ace4-00d1beb1370c\",\"name\":null,\"partitionColumns\":[\"instance_name\",\"k_factor\",\"has_closed_cycle\",\"model_name\"],\"schemaString\":\"{\\\"type\\\":\\\"struct\\\",\\\"fields\\\":[{\\\"name\\\":\\\"experiment_id\\\",\\\"type\\\":\\\"string\\\",\\\"nullable\\\":true,\\\"metadata\\\":{}},{\\\"name\\\":\\\"experiment_name\\\",\\\"type\\\":\\\"string\\\",\\\"nullable\\\":true,\\\"metadata\\\":{}},{\\\"name\\\":\\\"instance_name\\\",\\\"type\\\":\\\"string\\\",\\\"nullable\\\":true,\\\"metadata\\\":{}},{\\\"name\\\":\\\"k_factor\\\",\\\"type\\\":\\\"double\\\",\\\"nullable\\\":true,\\\"metadata\\\":{}},{\\\"name\\\":\\\"repetitions\\\",\\\"type\\\":\\\"long\\\",\\\"nullable\\\":true,\\\"metadata\\\":{}},{\\\"name\\\":\\\"model_name\\\",\\\"type\\\":\\\"string\\\",\\\"nullable\\\":true,\\\"metadata\\\":{}},{\\\"name\\\":\\\"has_closed_cycle\\\",\\\"type\\\":\\\"boolean\\\",\\\"nullable\\\":true,\\\"metadata\\\":{}},{\\\"name\\\":\\\"session_id\\\",\\\"type\\\":\\\"string\\\",\\\"nullable\\\":true,\\\"metadata\\\":{}},{\\\"name\\\":\\\"instance\\\",\\\"type\\\":{\\\"type\\\":\\\"struct\\\",\\\"fields\\\":[{\\\"name\\\":\\\"name\\\",\\\"type\\\":\\\"string\\\",\\\"nullable\\\":true,\\\"metadata\\\":{}},{\\\"name\\\":\\\"number_of_edges\\\",\\\"type\\\":\\\"long\\\",\\\"nullable\\\":true,\\\"metadata\\\":{}},{\\\"name\\\":\\\"number_of_vertices\\\",\\\"type\\\":\\\"long\\\",\\\"nullable\\\":true,\\\"metadata\\\":{}},{\\\"name\\\":\\\"symmetrical_type\\\",\\\"type\\\":\\\"string\\\",\\\"nullable\\\":true,\\\"metadata\\\":{}}]},\\\"nullable\\\":true,\\\"metadata\\\":{}},{\\\"name\\\":\\\"model\\\",\\\"type\\\":{\\\"type\\\":\\\"struct\\\",\\\"fields\\\":[{\\\"name\\\":\\\"name\\\",\\\"type\\\":\\\"string\\\",\\\"nullable\\\":true,\\\"metadata\\\":{}}]},\\\"nullable\\\":true,\\\"metadata\\\":{}},{\\\"name\\\":\\\"path_vertices\\\",\\\"type\\\":{\\\"type\\\":\\\"array\\\",\\\"elementType\\\":\\\"long\\\",\\\"containsNull\\\":true},\\\"nullable\\\":true,\\\"metadata\\\":{}},{\\\"name\\\":\\\"path_length\\\",\\\"type\\\":\\\"long\\\",\\\"nullable\\\":true,\\\"metadata\\\":{}},{\\\"name\\\":\\\"k_size\\\",\\\"type\\\":\\\"long\\\",\\\"nullable\\\":true,\\\"metadata\\\":{}}]}\"}","protocol":"{\"minReaderVersion\":1,\"minWriterVersion\":2}","mode":"ErrorIfExists","location":"file:///home/leonichel/k-tsp-solver/results/soa_replication/59da1476-4276-11f0-a63e-7cc25567a3b2"},"clientVersion":"delta-rs.0.17.3"}}