{"protocol":{"minReaderVersion":1,"minWriterVersion":2}}
{"metaData":{"id":"9392c788-11bb-4541-ade0-09a7cd86954f","name":null,"description":null,"format":{"provider":"parquet","options":{}},"schemaString":"{\"type\":\"struct\",\"fields\":[{\"name\":\"experiment_id\",\"type\":\"string\",\"nullable\":true,\"metadata\":{}},{\"name\":\"experiment_name\",\"type\":\"string\",\"nullable\":true,\"metadata\":{}},{\"name\":\"instance_name\",\"type\":\"string\",\"nullable\":true,\"metadata\":{}},{\"name\":\"k_factor\",\"type\":\"double\",\"nullable\":true,\"metadata\":{}},{\"name\":\"repetitions\",\"type\":\"long\",\"nullable\":true,\"metadata\":{}},{\"name\":\"model_name\",\"type\":\"string\",\"nullable\":true,\"metadata\":{}},{\"name\":\"has_closed_cycle\",\"type\":\"boolean\",\"nullable\":true,\"metadata\":{}},{\"name\":\"session_id\",\"type\":\"string\",\"nullable\":true,\"metadata\":{}},{\"name\":\"instance\",\"type\":{\"type\":\"struct\",\"fields\":[{\"name\":\"name\",\"type\":\"string\",\"nullable\":true,\"metadata\":{}},{\"name\":\"number_of_edges\",\"type\":\"long\",\"nullable\":true,\"metadata\":{}},{\"name\":\"number_of_vertices\",\"type\":\"long\",\"nullable\":true,\"metadata\":{}},{\"name\":\"symmetrical_type\",\"type\":\"string\",\"nullable\":true,\"metadata\":{}}]},\"nullable\":true,\"metadata\":{}},{\"name\":\"model\",\"type\":{\"type\":\"struct\",\"fields\":[{\"name\":\"name\",\"type\":\"string\",\"nullable\":true,\"metadata\":{}}]},\"nullable\":true,\"metadata\":{}},{\"name\":\"path_vertices\",\"type\":{\"type\":\"array\",\"elementType\":\"long\",\"containsNull\":true},\"nullable\":true,\"metadata\":{}},{\"name\":\"path_length\",\"type\":\"long\",\"nullable\":true,\"metadata\":{}},{\"name\":\"k_size\",\"type\":\"long\",\"nullable\":true,\"metadata\":{}}]}","partitionColumns":[],"createdTime":1747867451098,"configuration":{}}}
{"add":{"path":"0-307864a3-7488-4494-a76a-0b1b9c079f96-0.parquet","partitionValues":{},"size":7444,"modificationTime":1747867451098,"dataChange":true,"stats":"{\"numRecords\": 10, \"minValues\": {\"experiment_id\": \"1cda3da4-3695-11f0-aabf-b42e99f13130\", \"experiment_name\": \"variable_mutate_rate__replacement_operator\", \"instance_name\": \"ftv55.atsp\", \"k_factor\": 0.75, \"repetitions\": 10, \"model_name\": \"NearestNeighbors\", \"has_closed_cycle\": true, \"session_id\": \"1cde7b62-3695-11f0-aabf-b42e99f13130\", \"instance.name\": \"ftv55.atsp\", \"instance.number_of_edges\": 3136, \"instance.number_of_vertices\": 56, \"instance.symmetrical_type\": \"ATSP\", \"model.name\": \"NearestNeighbors\", \"path_vertices.list.item\": 0, \"path_length\": 1310, \"k_size\": 42}, \"maxValues\": {\"experiment_id\": \"1cda3da4-3695-11f0-aabf-b42e99f13130\", \"experiment_name\": \"variable_mutate_rate__replacement_operator\", \"instance_name\": \"ftv55.atsp\", \"k_factor\": 0.75, \"repetitions\": 10, \"model_name\": \"NearestNeighbors\", \"has_closed_cycle\": true, \"session_id\": \"1cdf2a62-3695-11f0-aabf-b42e99f13130\", \"instance.name\": \"ftv55.atsp\", \"instance.number_of_edges\": 3136, \"instance.number_of_vertices\": 56, \"instance.symmetrical_type\": \"ATSP\", \"model.name\": \"NearestNeighbors\", \"path_vertices.list.item\": 55, \"path_length\": 1310, \"k_size\": 42}, \"nullCount\": {\"experiment_id\": 0, \"experiment_name\": 0, \"instance_name\": 0, \"k_factor\": 0, \"repetitions\": 0, \"model_name\": 0, \"has_closed_cycle\": 0, \"session_id\": 0, \"instance.name\": 0, \"instance.number_of_edges\": 0, \"instance.number_of_vertices\": 0, \"instance.symmetrical_type\": 0, \"model.name\": 0, \"path_vertices.list.item\": 0, \"path_length\": 0, \"k_size\": 0}}","tags":null,"deletionVector":null,"baseRowId":null,"defaultRowCommitVersion":null,"clusteringProvider":null}}
{"commitInfo":{"timestamp":1747867451098,"operation":"CREATE TABLE","operationParameters":{"location":"file:///home/leonichel/k-tsp-solver/results/variable_mutate_rate__replacement_operator/1cda3da4-3695-11f0-aabf-b42e99f13130","metadata":"{\"configuration\":{},\"createdTime\":1747867451098,\"description\":null,\"format\":{\"options\":{},\"provider\":\"parquet\"},\"id\":\"9392c788-11bb-4541-ade0-09a7cd86954f\",\"name\":null,\"partitionColumns\":[],\"schemaString\":\"{\\\"type\\\":\\\"struct\\\",\\\"fields\\\":[{\\\"name\\\":\\\"experiment_id\\\",\\\"type\\\":\\\"string\\\",\\\"nullable\\\":true,\\\"metadata\\\":{}},{\\\"name\\\":\\\"experiment_name\\\",\\\"type\\\":\\\"string\\\",\\\"nullable\\\":true,\\\"metadata\\\":{}},{\\\"name\\\":\\\"instance_name\\\",\\\"type\\\":\\\"string\\\",\\\"nullable\\\":true,\\\"metadata\\\":{}},{\\\"name\\\":\\\"k_factor\\\",\\\"type\\\":\\\"double\\\",\\\"nullable\\\":true,\\\"metadata\\\":{}},{\\\"name\\\":\\\"repetitions\\\",\\\"type\\\":\\\"long\\\",\\\"nullable\\\":true,\\\"metadata\\\":{}},{\\\"name\\\":\\\"model_name\\\",\\\"type\\\":\\\"string\\\",\\\"nullable\\\":true,\\\"metadata\\\":{}},{\\\"name\\\":\\\"has_closed_cycle\\\",\\\"type\\\":\\\"boolean\\\",\\\"nullable\\\":true,\\\"metadata\\\":{}},{\\\"name\\\":\\\"session_id\\\",\\\"type\\\":\\\"string\\\",\\\"nullable\\\":true,\\\"metadata\\\":{}},{\\\"name\\\":\\\"instance\\\",\\\"type\\\":{\\\"type\\\":\\\"struct\\\",\\\"fields\\\":[{\\\"name\\\":\\\"name\\\",\\\"type\\\":\\\"string\\\",\\\"nullable\\\":true,\\\"metadata\\\":{}},{\\\"name\\\":\\\"number_of_edges\\\",\\\"type\\\":\\\"long\\\",\\\"nullable\\\":true,\\\"metadata\\\":{}},{\\\"name\\\":\\\"number_of_vertices\\\",\\\"type\\\":\\\"long\\\",\\\"nullable\\\":true,\\\"metadata\\\":{}},{\\\"name\\\":\\\"symmetrical_type\\\",\\\"type\\\":\\\"string\\\",\\\"nullable\\\":true,\\\"metadata\\\":{}}]},\\\"nullable\\\":true,\\\"metadata\\\":{}},{\\\"name\\\":\\\"model\\\",\\\"type\\\":{\\\"type\\\":\\\"struct\\\",\\\"fields\\\":[{\\\"name\\\":\\\"name\\\",\\\"type\\\":\\\"string\\\",\\\"nullable\\\":true,\\\"metadata\\\":{}}]},\\\"nullable\\\":true,\\\"metadata\\\":{}},{\\\"name\\\":\\\"path_vertices\\\",\\\"type\\\":{\\\"type\\\":\\\"array\\\",\\\"elementType\\\":\\\"long\\\",\\\"containsNull\\\":true},\\\"nullable\\\":true,\\\"metadata\\\":{}},{\\\"name\\\":\\\"path_length\\\",\\\"type\\\":\\\"long\\\",\\\"nullable\\\":true,\\\"metadata\\\":{}},{\\\"name\\\":\\\"k_size\\\",\\\"type\\\":\\\"long\\\",\\\"nullable\\\":true,\\\"metadata\\\":{}}]}\"}","mode":"ErrorIfExists","protocol":"{\"minReaderVersion\":1,\"minWriterVersion\":2}"},"clientVersion":"delta-rs.0.17.3"}}