{"add":{"path":"instance_name=ch130.tsp/k_factor=0.5/has_closed_cycle=true/model_name=GeneticAlgorithmNearestNeighborsEnsemble/2283-f4aa8183-f252-4121-8a08-2a3cc2d3f5b3-0.parquet","partitionValues":{"k_factor":"0.5","instance_name":"ch130.tsp","model_name":"GeneticAlgorithmNearestNeighborsEnsemble","has_closed_cycle":"true"},"size":4654,"modificationTime":1745989174105,"dataChange":true,"stats":"{\"numRecords\": 1, \"minValues\": {\"session_id\": \"e85e9b9a-257f-11f0-9e00-8b9131474639\", \"instance_number_of_vertices\": 130, \"instance_number_of_edges\": 8515, \"instance_symmetrical_type\": \"TSP\", \"model\": \"{'name': 'NearestNeighbors'}\", \"path_vertices.list.item\": 1, \"path_length\": 2680, \"k_size\": 65, \"experiment_id\": \"db201eb9-257f-11f0-9e00-8b9131474639\"}, \"maxValues\": {\"session_id\": \"e85e9b9a-257f-11f0-9e00-8b9131474639\", \"instance_number_of_vertices\": 130, \"instance_number_of_edges\": 8515, \"instance_symmetrical_type\": \"TSP\", \"model\": \"{'name': 'NearestNeighbors'}\", \"path_vertices.list.item\": 130, \"path_length\": 2680, \"k_size\": 65, \"experiment_id\": \"db201eb9-257f-11f0-9e00-8b9131474639\"}, \"nullCount\": {\"session_id\": 0, \"instance_number_of_vertices\": 0, \"instance_number_of_edges\": 0, \"instance_symmetrical_type\": 0, \"model\": 0, \"path_vertices.list.item\": 0, \"path_length\": 0, \"k_size\": 0, \"experiment_id\": 0}}","tags":null,"deletionVector":null,"baseRowId":null,"defaultRowCommitVersion":null,"clusteringProvider":null}}
{"commitInfo":{"timestamp":1745989174105,"operation":"WRITE","operationParameters":{"partitionBy":"[\"instance_name\",\"k_factor\",\"has_closed_cycle\",\"model_name\"]","mode":"Append"},"clientVersion":"delta-rs.0.17.3"}}