{"add":{"path":"instance_name=att532.tsp/k_factor=0.75/has_closed_cycle=true/model_name=GeneticAlgorithmNearestNeighborsEnsemble/1987-a4d87335-191f-42c0-b949-88391e4e8341-0.parquet","partitionValues":{"model_name":"GeneticAlgorithmNearestNeighborsEnsemble","instance_name":"att532.tsp","k_factor":"0.75","has_closed_cycle":"true"},"size":6390,"modificationTime":1745986252574,"dataChange":true,"stats":"{\"numRecords\": 1, \"minValues\": {\"session_id\": \"1b1621d6-2579-11f0-9dfe-8b9131474639\", \"instance_number_of_vertices\": 532, \"instance_number_of_edges\": 141778, \"instance_symmetrical_type\": \"TSP\", \"model\": \"{'name': 'NearestNeighbors'}\", \"path_vertices.list.item\": 8, \"path_length\": 20210, \"k_size\": 399, \"experiment_id\": \"ffd71373-2577-11f0-9dfe-8b9131474639\"}, \"maxValues\": {\"session_id\": \"1b1621d6-2579-11f0-9dfe-8b9131474639\", \"instance_number_of_vertices\": 532, \"instance_number_of_edges\": 141778, \"instance_symmetrical_type\": \"TSP\", \"model\": \"{'name': 'NearestNeighbors'}\", \"path_vertices.list.item\": 532, \"path_length\": 20210, \"k_size\": 399, \"experiment_id\": \"ffd71373-2577-11f0-9dfe-8b9131474639\"}, \"nullCount\": {\"session_id\": 0, \"instance_number_of_vertices\": 0, \"instance_number_of_edges\": 0, \"instance_symmetrical_type\": 0, \"model\": 0, \"path_vertices.list.item\": 0, \"path_length\": 0, \"k_size\": 0, \"experiment_id\": 0}}","tags":null,"deletionVector":null,"baseRowId":null,"defaultRowCommitVersion":null,"clusteringProvider":null}}
{"commitInfo":{"timestamp":1745986252574,"operation":"WRITE","operationParameters":{"mode":"Append","partitionBy":"[\"instance_name\",\"k_factor\",\"has_closed_cycle\",\"model_name\"]"},"clientVersion":"delta-rs.0.17.3"}}