{"add":{"path":"instance_name=gr24.tsp/k_factor=0.25/has_closed_cycle=true/model_name=GeneticAlgorithmNearestNeighborsEnsemble/3349-5a39a5dd-3d80-4a97-bad4-36f0710de3cf-0.parquet","partitionValues":{"instance_name":"gr24.tsp","has_closed_cycle":"true","model_name":"GeneticAlgorithmNearestNeighborsEnsemble","k_factor":"0.25"},"size":4350,"modificationTime":1745996928419,"dataChange":true,"stats":"{\"numRecords\": 1, \"minValues\": {\"session_id\": \"f64efef4-2591-11f0-9e09-8b9131474639\", \"instance_number_of_vertices\": 24, \"instance_number_of_edges\": 300, \"instance_symmetrical_type\": \"TSP\", \"model\": \"{'name': 'NearestNeighbors'}\", \"path_vertices.list.item\": 5, \"path_length\": 152, \"k_size\": 6, \"experiment_id\": \"f5513ecc-2591-11f0-9e09-8b9131474639\"}, \"maxValues\": {\"session_id\": \"f64efef4-2591-11f0-9e09-8b9131474639\", \"instance_number_of_vertices\": 24, \"instance_number_of_edges\": 300, \"instance_symmetrical_type\": \"TSP\", \"model\": \"{'name': 'NearestNeighbors'}\", \"path_vertices.list.item\": 23, \"path_length\": 152, \"k_size\": 6, \"experiment_id\": \"f5513ecc-2591-11f0-9e09-8b9131474639\"}, \"nullCount\": {\"session_id\": 0, \"instance_number_of_vertices\": 0, \"instance_number_of_edges\": 0, \"instance_symmetrical_type\": 0, \"model\": 0, \"path_vertices.list.item\": 0, \"path_length\": 0, \"k_size\": 0, \"experiment_id\": 0}}","tags":null,"deletionVector":null,"baseRowId":null,"defaultRowCommitVersion":null,"clusteringProvider":null}}
{"commitInfo":{"timestamp":1745996928419,"operation":"WRITE","operationParameters":{"mode":"Append","partitionBy":"[\"instance_name\",\"k_factor\",\"has_closed_cycle\",\"model_name\"]"},"clientVersion":"delta-rs.0.17.3"}}