{"add":{"path":"instance_name=rbg403.atsp/k_factor=0.5/has_closed_cycle=false/model_name=GeneticAlgorithmNearestNeighborsEnsemble/2695-8413e379-acc3-4eaa-ac19-ae74a0e044d2-0.parquet","partitionValues":{"k_factor":"0.5","has_closed_cycle":"false","instance_name":"rbg403.atsp","model_name":"GeneticAlgorithmNearestNeighborsEnsemble"},"size":5362,"modificationTime":1745992786523,"dataChange":true,"stats":"{\"numRecords\": 1, \"minValues\": {\"session_id\": \"519c2a0c-2588-11f0-9e07-8b9131474639\", \"instance_number_of_vertices\": 403, \"instance_number_of_edges\": 162409, \"instance_symmetrical_type\": \"ATSP\", \"model\": \"{'name': 'NearestNeighbors'}\", \"path_vertices.list.item\": 0, \"path_length\": 533, \"k_size\": 201, \"experiment_id\": \"325e8ca3-2588-11f0-9e07-8b9131474639\"}, \"maxValues\": {\"session_id\": \"519c2a0c-2588-11f0-9e07-8b9131474639\", \"instance_number_of_vertices\": 403, \"instance_number_of_edges\": 162409, \"instance_symmetrical_type\": \"ATSP\", \"model\": \"{'name': 'NearestNeighbors'}\", \"path_vertices.list.item\": 394, \"path_length\": 533, \"k_size\": 201, \"experiment_id\": \"325e8ca3-2588-11f0-9e07-8b9131474639\"}, \"nullCount\": {\"session_id\": 0, \"instance_number_of_vertices\": 0, \"instance_number_of_edges\": 0, \"instance_symmetrical_type\": 0, \"model\": 0, \"path_vertices.list.item\": 0, \"path_length\": 0, \"k_size\": 0, \"experiment_id\": 0}}","tags":null,"deletionVector":null,"baseRowId":null,"defaultRowCommitVersion":null,"clusteringProvider":null}}
{"commitInfo":{"timestamp":1745992786523,"operation":"WRITE","operationParameters":{"partitionBy":"[\"instance_name\",\"k_factor\",\"has_closed_cycle\",\"model_name\"]","mode":"Append"},"clientVersion":"delta-rs.0.17.3"}}