{"add":{"path":"instance_name=br17.atsp/k_factor=0.25/has_closed_cycle=true/model_name=GeneticAlgorithmNearestNeighborsEnsemble/2245-d93db3a8-7572-407b-bcf1-8a346a87f7cf-0.parquet","partitionValues":{"has_closed_cycle":"true","instance_name":"br17.atsp","k_factor":"0.25","model_name":"GeneticAlgorithmNearestNeighborsEnsemble"},"size":4349,"modificationTime":1745988862997,"dataChange":true,"stats":"{\"numRecords\": 1, \"minValues\": {\"session_id\": \"2ef4544c-257f-11f0-9dff-8b9131474639\", \"instance_number_of_vertices\": 17, \"instance_number_of_edges\": 289, \"instance_symmetrical_type\": \"ATSP\", \"model\": \"{'name': 'NearestNeighbors'}\", \"path_vertices.list.item\": 1, \"path_length\": 0, \"k_size\": 4, \"experiment_id\": \"2d7bfdaf-257f-11f0-9dff-8b9131474639\"}, \"maxValues\": {\"session_id\": \"2ef4544c-257f-11f0-9dff-8b9131474639\", \"instance_number_of_vertices\": 17, \"instance_number_of_edges\": 289, \"instance_symmetrical_type\": \"ATSP\", \"model\": \"{'name': 'NearestNeighbors'}\", \"path_vertices.list.item\": 10, \"path_length\": 0, \"k_size\": 4, \"experiment_id\": \"2d7bfdaf-257f-11f0-9dff-8b9131474639\"}, \"nullCount\": {\"session_id\": 0, \"instance_number_of_vertices\": 0, \"instance_number_of_edges\": 0, \"instance_symmetrical_type\": 0, \"model\": 0, \"path_vertices.list.item\": 0, \"path_length\": 0, \"k_size\": 0, \"experiment_id\": 0}}","tags":null,"deletionVector":null,"baseRowId":null,"defaultRowCommitVersion":null,"clusteringProvider":null}}
{"commitInfo":{"timestamp":1745988862998,"operation":"WRITE","operationParameters":{"mode":"Append","partitionBy":"[\"instance_name\",\"k_factor\",\"has_closed_cycle\",\"model_name\"]"},"clientVersion":"delta-rs.0.17.3"}}