{"protocol":{"minReaderVersion":1,"minWriterVersion":2}}
{"metaData":{"id":"c2cc619c-ac1c-47d7-83a4-517f77d63b44","name":null,"description":null,"format":{"provider":"parquet","options":{}},"schemaString":"{\"type\":\"struct\",\"fields\":[{\"name\":\"experiment_id\",\"type\":\"string\",\"nullable\":true,\"metadata\":{}},{\"name\":\"experiment_name\",\"type\":\"string\",\"nullable\":true,\"metadata\":{}},{\"name\":\"instance_name\",\"type\":\"string\",\"nullable\":true,\"metadata\":{}},{\"name\":\"k_factor\",\"type\":\"double\",\"nullable\":true,\"metadata\":{}},{\"name\":\"repetitions\",\"type\":\"long\",\"nullable\":true,\"metadata\":{}},{\"name\":\"model_name\",\"type\":\"string\",\"nullable\":true,\"metadata\":{}},{\"name\":\"has_closed_cycle\",\"type\":\"boolean\",\"nullable\":true,\"metadata\":{}},{\"name\":\"session_id\",\"type\":\"string\",\"nullable\":true,\"metadata\":{}},{\"name\":\"instance\",\"type\":{\"type\":\"struct\",\"fields\":[{\"name\":\"name\",\"type\":\"string\",\"nullable\":true,\"metadata\":{}},{\"name\":\"number_of_edges\",\"type\":\"long\",\"nullable\":true,\"metadata\":{}},{\"name\":\"number_of_vertices\",\"type\":\"long\",\"nullable\":true,\"metadata\":{}},{\"name\":\"symmetrical_type\",\"type\":\"string\",\"nullable\":true,\"metadata\":{}}]},\"nullable\":true,\"metadata\":{}},{\"name\":\"model\",\"type\":{\"type\":\"struct\",\"fields\":[{\"name\":\"name\",\"type\":\"string\",\"nullable\":true,\"metadata\":{}}]},\"nullable\":true,\"metadata\":{}},{\"name\":\"path_vertices\",\"type\":{\"type\":\"array\",\"elementType\":\"long\",\"containsNull\":true},\"nullable\":true,\"metadata\":{}},{\"name\":\"path_length\",\"type\":\"long\",\"nullable\":true,\"metadata\":{}},{\"name\":\"k_size\",\"type\":\"long\",\"nullable\":true,\"metadata\":{}}]}","partitionColumns":[],"createdTime":1747861123621,"configuration":{}}}
{"add":{"path":"0-ae25e97b-ec52-4d10-8482-0073a233ea2b-0.parquet","partitionValues":{},"size":8399,"modificationTime":1747861123620,"dataChange":true,"stats":"{\"numRecords\": 10, \"minValues\": {\"experiment_id\": \"5ea4c588-3686-11f0-905c-b42e99f13130\", \"experiment_name\": \"variable_mutate_rate__replacement_operator\", \"instance_name\": \"gr431.tsp\", \"k_factor\": 0.5, \"repetitions\": 10, \"model_name\": \"NearestNeighbors\", \"has_closed_cycle\": false, \"session_id\": \"605d3022-3686-11f0-905c-b42e99f13130\", \"instance.name\": \"gr431.tsp\", \"instance.number_of_edges\": 93096, \"instance.number_of_vertices\": 431, \"instance.symmetrical_type\": \"TSP\", \"model.name\": \"NearestNeighbors\", \"path_vertices.list.item\": 2, \"path_length\": 54451, \"k_size\": 215}, \"maxValues\": {\"experiment_id\": \"5ea4c588-3686-11f0-905c-b42e99f13130\", \"experiment_name\": \"variable_mutate_rate__replacement_operator\", \"instance_name\": \"gr431.tsp\", \"k_factor\": 0.5, \"repetitions\": 10, \"model_name\": \"NearestNeighbors\", \"has_closed_cycle\": false, \"session_id\": \"616072c2-3686-11f0-905c-b42e99f13130\", \"instance.name\": \"gr431.tsp\", \"instance.number_of_edges\": 93096, \"instance.number_of_vertices\": 431, \"instance.symmetrical_type\": \"TSP\", \"model.name\": \"NearestNeighbors\", \"path_vertices.list.item\": 400, \"path_length\": 54451, \"k_size\": 215}, \"nullCount\": {\"experiment_id\": 0, \"experiment_name\": 0, \"instance_name\": 0, \"k_factor\": 0, \"repetitions\": 0, \"model_name\": 0, \"has_closed_cycle\": 0, \"session_id\": 0, \"instance.name\": 0, \"instance.number_of_edges\": 0, \"instance.number_of_vertices\": 0, \"instance.symmetrical_type\": 0, \"model.name\": 0, \"path_vertices.list.item\": 0, \"path_length\": 0, \"k_size\": 0}}","tags":null,"deletionVector":null,"baseRowId":null,"defaultRowCommitVersion":null,"clusteringProvider":null}}
{"commitInfo":{"timestamp":1747861123621,"operation":"CREATE TABLE","operationParameters":{"protocol":"{\"minReaderVersion\":1,\"minWriterVersion\":2}","mode":"ErrorIfExists","location":"file:///home/leonichel/k-tsp-solver/results/variable_mutate_rate__replacement_operator/5ea4c588-3686-11f0-905c-b42e99f13130","metadata":"{\"configuration\":{},\"createdTime\":1747861123621,\"description\":null,\"format\":{\"options\":{},\"provider\":\"parquet\"},\"id\":\"c2cc619c-ac1c-47d7-83a4-517f77d63b44\",\"name\":null,\"partitionColumns\":[],\"schemaString\":\"{\\\"type\\\":\\\"struct\\\",\\\"fields\\\":[{\\\"name\\\":\\\"experiment_id\\\",\\\"type\\\":\\\"string\\\",\\\"nullable\\\":true,\\\"metadata\\\":{}},{\\\"name\\\":\\\"experiment_name\\\",\\\"type\\\":\\\"string\\\",\\\"nullable\\\":true,\\\"metadata\\\":{}},{\\\"name\\\":\\\"instance_name\\\",\\\"type\\\":\\\"string\\\",\\\"nullable\\\":true,\\\"metadata\\\":{}},{\\\"name\\\":\\\"k_factor\\\",\\\"type\\\":\\\"double\\\",\\\"nullable\\\":true,\\\"metadata\\\":{}},{\\\"name\\\":\\\"repetitions\\\",\\\"type\\\":\\\"long\\\",\\\"nullable\\\":true,\\\"metadata\\\":{}},{\\\"name\\\":\\\"model_name\\\",\\\"type\\\":\\\"string\\\",\\\"nullable\\\":true,\\\"metadata\\\":{}},{\\\"name\\\":\\\"has_closed_cycle\\\",\\\"type\\\":\\\"boolean\\\",\\\"nullable\\\":true,\\\"metadata\\\":{}},{\\\"name\\\":\\\"session_id\\\",\\\"type\\\":\\\"string\\\",\\\"nullable\\\":true,\\\"metadata\\\":{}},{\\\"name\\\":\\\"instance\\\",\\\"type\\\":{\\\"type\\\":\\\"struct\\\",\\\"fields\\\":[{\\\"name\\\":\\\"name\\\",\\\"type\\\":\\\"string\\\",\\\"nullable\\\":true,\\\"metadata\\\":{}},{\\\"name\\\":\\\"number_of_edges\\\",\\\"type\\\":\\\"long\\\",\\\"nullable\\\":true,\\\"metadata\\\":{}},{\\\"name\\\":\\\"number_of_vertices\\\",\\\"type\\\":\\\"long\\\",\\\"nullable\\\":true,\\\"metadata\\\":{}},{\\\"name\\\":\\\"symmetrical_type\\\",\\\"type\\\":\\\"string\\\",\\\"nullable\\\":true,\\\"metadata\\\":{}}]},\\\"nullable\\\":true,\\\"metadata\\\":{}},{\\\"name\\\":\\\"model\\\",\\\"type\\\":{\\\"type\\\":\\\"struct\\\",\\\"fields\\\":[{\\\"name\\\":\\\"name\\\",\\\"type\\\":\\\"string\\\",\\\"nullable\\\":true,\\\"metadata\\\":{}}]},\\\"nullable\\\":true,\\\"metadata\\\":{}},{\\\"name\\\":\\\"path_vertices\\\",\\\"type\\\":{\\\"type\\\":\\\"array\\\",\\\"elementType\\\":\\\"long\\\",\\\"containsNull\\\":true},\\\"nullable\\\":true,\\\"metadata\\\":{}},{\\\"name\\\":\\\"path_length\\\",\\\"type\\\":\\\"long\\\",\\\"nullable\\\":true,\\\"metadata\\\":{}},{\\\"name\\\":\\\"k_size\\\",\\\"type\\\":\\\"long\\\",\\\"nullable\\\":true,\\\"metadata\\\":{}}]}\"}"},"clientVersion":"delta-rs.0.17.3"}}