{"protocol":{"minReaderVersion":1,"minWriterVersion":2}}
{"metaData":{"id":"ddbee420-b7e2-460d-a8ab-3ecbc7d4c7b4","name":null,"description":null,"format":{"provider":"parquet","options":{}},"schemaString":"{\"type\":\"struct\",\"fields\":[{\"name\":\"experiment_id\",\"type\":\"string\",\"nullable\":true,\"metadata\":{}},{\"name\":\"experiment_name\",\"type\":\"string\",\"nullable\":true,\"metadata\":{}},{\"name\":\"instance_name\",\"type\":\"string\",\"nullable\":true,\"metadata\":{}},{\"name\":\"k_factor\",\"type\":\"double\",\"nullable\":true,\"metadata\":{}},{\"name\":\"repetitions\",\"type\":\"long\",\"nullable\":true,\"metadata\":{}},{\"name\":\"model_name\",\"type\":\"string\",\"nullable\":true,\"metadata\":{}},{\"name\":\"has_closed_cycle\",\"type\":\"boolean\",\"nullable\":true,\"metadata\":{}},{\"name\":\"session_id\",\"type\":\"string\",\"nullable\":true,\"metadata\":{}},{\"name\":\"instance\",\"type\":{\"type\":\"struct\",\"fields\":[{\"name\":\"name\",\"type\":\"string\",\"nullable\":true,\"metadata\":{}},{\"name\":\"number_of_edges\",\"type\":\"long\",\"nullable\":true,\"metadata\":{}},{\"name\":\"number_of_vertices\",\"type\":\"long\",\"nullable\":true,\"metadata\":{}},{\"name\":\"symmetrical_type\",\"type\":\"string\",\"nullable\":true,\"metadata\":{}}]},\"nullable\":true,\"metadata\":{}},{\"name\":\"model\",\"type\":{\"type\":\"struct\",\"fields\":[{\"name\":\"generations\",\"type\":\"long\",\"nullable\":true,\"metadata\":{}},{\"name\":\"mutation_operator_probabilities\",\"type\":{\"type\":\"array\",\"elementType\":\"double\",\"containsNull\":true},\"nullable\":true,\"metadata\":{}},{\"name\":\"mutation_rate\",\"type\":\"double\",\"nullable\":true,\"metadata\":{}},{\"name\":\"name\",\"type\":\"string\",\"nullable\":true,\"metadata\":{}},{\"name\":\"population_size\",\"type\":\"long\",\"nullable\":true,\"metadata\":{}},{\"name\":\"selection_size\",\"type\":\"long\",\"nullable\":true,\"metadata\":{}},{\"name\":\"use_crossover\",\"type\":\"boolean\",\"nullable\":true,\"metadata\":{}}]},\"nullable\":true,\"metadata\":{}},{\"name\":\"path_vertices\",\"type\":{\"type\":\"array\",\"elementType\":\"long\",\"containsNull\":true},\"nullable\":true,\"metadata\":{}},{\"name\":\"path_length\",\"type\":\"long\",\"nullable\":true,\"metadata\":{}},{\"name\":\"k_size\",\"type\":\"long\",\"nullable\":true,\"metadata\":{}}]}","partitionColumns":["instance_name","k_factor","has_closed_cycle","model_name"],"createdTime":1749178360373,"configuration":{}}}
{"add":{"path":"instance_name=ftv33.atsp/k_factor=0.75/has_closed_cycle=false/model_name=GeneticAlgorithmNearestNeighborsEnsemble/0-dc42d954-89d5-489d-9a63-531030e1cd98-0.parquet","partitionValues":{"k_factor":"0.75","has_closed_cycle":"false","instance_name":"ftv33.atsp","model_name":"GeneticAlgorithmNearestNeighborsEnsemble"},"size":9219,"modificationTime":1749178360370,"dataChange":true,"stats":"{\"numRecords\": 30, \"minValues\": {\"experiment_id\": \"4a164856-4281-11f0-8488-7cc25567a3b2\", \"experiment_name\": \"change__variable_mutate_rate__replacement_operator\", \"repetitions\": 30, \"session_id\": \"4ab14c70-4281-11f0-8488-7cc25567a3b2\", \"instance.name\": \"ftv33.atsp\", \"instance.number_of_edges\": 1156, \"instance.number_of_vertices\": 34, \"instance.symmetrical_type\": \"ATSP\", \"model.generations\": 100, \"model.mutation_operator_probabilities.list.item\": 0.25, \"model.mutation_rate\": 0.040000000000000036, \"model.name\": \"GeneticAlgorithmNearestNeighborsEnsemble\", \"model.population_size\": 100, \"model.selection_size\": 10, \"model.use_crossover\": false, \"path_vertices.list.item\": 0, \"path_length\": 832, \"k_size\": 25}, \"maxValues\": {\"experiment_id\": \"4a164856-4281-11f0-8488-7cc25567a3b2\", \"experiment_name\": \"change__variable_mutate_rate__replacement_operator\", \"repetitions\": 30, \"session_id\": \"4fafb5b8-4281-11f0-8488-7cc25567a3b2\", \"instance.name\": \"ftv33.atsp\", \"instance.number_of_edges\": 1156, \"instance.number_of_vertices\": 34, \"instance.symmetrical_type\": \"ATSP\", \"model.generations\": 100, \"model.mutation_operator_probabilities.list.item\": 0.25, \"model.mutation_rate\": 0.08999999999999997, \"model.name\": \"GeneticAlgorithmNearestNeighborsEnsemble\", \"model.population_size\": 100, \"model.selection_size\": 10, \"model.use_crossover\": false, \"path_vertices.list.item\": 33, \"path_length\": 868, \"k_size\": 25}, \"nullCount\": {\"experiment_id\": 0, \"experiment_name\": 0, \"repetitions\": 0, \"session_id\": 0, \"instance.name\": 0, \"instance.number_of_edges\": 0, \"instance.number_of_vertices\": 0, \"instance.symmetrical_type\": 0, \"model.generations\": 25, \"model.mutation_operator_probabilities.list.item\": 25, \"model.mutation_rate\": 25, \"model.name\": 0, \"model.population_size\": 25, \"model.selection_size\": 25, \"model.use_crossover\": 25, \"path_vertices.list.item\": 0, \"path_length\": 0, \"k_size\": 0}}","tags":null,"deletionVector":null,"baseRowId":null,"defaultRowCommitVersion":null,"clusteringProvider":null}}
{"commitInfo":{"timestamp":1749178360374,"operation":"CREATE TABLE","operationParameters":{"metadata":"{\"configuration\":{},\"createdTime\":1749178360373,\"description\":null,\"format\":{\"options\":{},\"provider\":\"parquet\"},\"id\":\"ddbee420-b7e2-460d-a8ab-3ecbc7d4c7b4\",\"name\":null,\"partitionColumns\":[\"instance_name\",\"k_factor\",\"has_closed_cycle\",\"model_name\"],\"schemaString\":\"{\\\"type\\\":\\\"struct\\\",\\\"fields\\\":[{\\\"name\\\":\\\"experiment_id\\\",\\\"type\\\":\\\"string\\\",\\\"nullable\\\":true,\\\"metadata\\\":{}},{\\\"name\\\":\\\"experiment_name\\\",\\\"type\\\":\\\"string\\\",\\\"nullable\\\":true,\\\"metadata\\\":{}},{\\\"name\\\":\\\"instance_name\\\",\\\"type\\\":\\\"string\\\",\\\"nullable\\\":true,\\\"metadata\\\":{}},{\\\"name\\\":\\\"k_factor\\\",\\\"type\\\":\\\"double\\\",\\\"nullable\\\":true,\\\"metadata\\\":{}},{\\\"name\\\":\\\"repetitions\\\",\\\"type\\\":\\\"long\\\",\\\"nullable\\\":true,\\\"metadata\\\":{}},{\\\"name\\\":\\\"model_name\\\",\\\"type\\\":\\\"string\\\",\\\"nullable\\\":true,\\\"metadata\\\":{}},{\\\"name\\\":\\\"has_closed_cycle\\\",\\\"type\\\":\\\"boolean\\\",\\\"nullable\\\":true,\\\"metadata\\\":{}},{\\\"name\\\":\\\"session_id\\\",\\\"type\\\":\\\"string\\\",\\\"nullable\\\":true,\\\"metadata\\\":{}},{\\\"name\\\":\\\"instance\\\",\\\"type\\\":{\\\"type\\\":\\\"struct\\\",\\\"fields\\\":[{\\\"name\\\":\\\"name\\\",\\\"type\\\":\\\"string\\\",\\\"nullable\\\":true,\\\"metadata\\\":{}},{\\\"name\\\":\\\"number_of_edges\\\",\\\"type\\\":\\\"long\\\",\\\"nullable\\\":true,\\\"metadata\\\":{}},{\\\"name\\\":\\\"number_of_vertices\\\",\\\"type\\\":\\\"long\\\",\\\"nullable\\\":true,\\\"metadata\\\":{}},{\\\"name\\\":\\\"symmetrical_type\\\",\\\"type\\\":\\\"string\\\",\\\"nullable\\\":true,\\\"metadata\\\":{}}]},\\\"nullable\\\":true,\\\"metadata\\\":{}},{\\\"name\\\":\\\"model\\\",\\\"type\\\":{\\\"type\\\":\\\"struct\\\",\\\"fields\\\":[{\\\"name\\\":\\\"generations\\\",\\\"type\\\":\\\"long\\\",\\\"nullable\\\":true,\\\"metadata\\\":{}},{\\\"name\\\":\\\"mutation_operator_probabilities\\\",\\\"type\\\":{\\\"type\\\":\\\"array\\\",\\\"elementType\\\":\\\"double\\\",\\\"containsNull\\\":true},\\\"nullable\\\":true,\\\"metadata\\\":{}},{\\\"name\\\":\\\"mutation_rate\\\",\\\"type\\\":\\\"double\\\",\\\"nullable\\\":true,\\\"metadata\\\":{}},{\\\"name\\\":\\\"name\\\",\\\"type\\\":\\\"string\\\",\\\"nullable\\\":true,\\\"metadata\\\":{}},{\\\"name\\\":\\\"population_size\\\",\\\"type\\\":\\\"long\\\",\\\"nullable\\\":true,\\\"metadata\\\":{}},{\\\"name\\\":\\\"selection_size\\\",\\\"type\\\":\\\"long\\\",\\\"nullable\\\":true,\\\"metadata\\\":{}},{\\\"name\\\":\\\"use_crossover\\\",\\\"type\\\":\\\"boolean\\\",\\\"nullable\\\":true,\\\"metadata\\\":{}}]},\\\"nullable\\\":true,\\\"metadata\\\":{}},{\\\"name\\\":\\\"path_vertices\\\",\\\"type\\\":{\\\"type\\\":\\\"array\\\",\\\"elementType\\\":\\\"long\\\",\\\"containsNull\\\":true},\\\"nullable\\\":true,\\\"metadata\\\":{}},{\\\"name\\\":\\\"path_length\\\",\\\"type\\\":\\\"long\\\",\\\"nullable\\\":true,\\\"metadata\\\":{}},{\\\"name\\\":\\\"k_size\\\",\\\"type\\\":\\\"long\\\",\\\"nullable\\\":true,\\\"metadata\\\":{}}]}\"}","location":"file:///home/leonichel/k-tsp-solver/results/change__variable_mutate_rate__replacement_operator/4a164856-4281-11f0-8488-7cc25567a3b2","mode":"ErrorIfExists","protocol":"{\"minReaderVersion\":1,\"minWriterVersion\":2}"},"clientVersion":"delta-rs.0.17.3"}}