{"protocol":{"minReaderVersion":1,"minWriterVersion":2}}
{"metaData":{"id":"50a5b5d9-1cd6-4e27-8111-3ca789f93271","name":null,"description":null,"format":{"provider":"parquet","options":{}},"schemaString":"{\"type\":\"struct\",\"fields\":[{\"name\":\"experiment_id\",\"type\":\"string\",\"nullable\":true,\"metadata\":{}},{\"name\":\"experiment_name\",\"type\":\"string\",\"nullable\":true,\"metadata\":{}},{\"name\":\"instance_name\",\"type\":\"string\",\"nullable\":true,\"metadata\":{}},{\"name\":\"k_factor\",\"type\":\"double\",\"nullable\":true,\"metadata\":{}},{\"name\":\"repetitions\",\"type\":\"long\",\"nullable\":true,\"metadata\":{}},{\"name\":\"model_name\",\"type\":\"string\",\"nullable\":true,\"metadata\":{}},{\"name\":\"has_closed_cycle\",\"type\":\"boolean\",\"nullable\":true,\"metadata\":{}},{\"name\":\"session_id\",\"type\":\"string\",\"nullable\":true,\"metadata\":{}},{\"name\":\"instance\",\"type\":{\"type\":\"struct\",\"fields\":[{\"name\":\"name\",\"type\":\"string\",\"nullable\":true,\"metadata\":{}},{\"name\":\"number_of_edges\",\"type\":\"long\",\"nullable\":true,\"metadata\":{}},{\"name\":\"number_of_vertices\",\"type\":\"long\",\"nullable\":true,\"metadata\":{}},{\"name\":\"symmetrical_type\",\"type\":\"string\",\"nullable\":true,\"metadata\":{}}]},\"nullable\":true,\"metadata\":{}},{\"name\":\"model\",\"type\":{\"type\":\"struct\",\"fields\":[{\"name\":\"name\",\"type\":\"string\",\"nullable\":true,\"metadata\":{}}]},\"nullable\":true,\"metadata\":{}},{\"name\":\"path_vertices\",\"type\":{\"type\":\"array\",\"elementType\":\"long\",\"containsNull\":true},\"nullable\":true,\"metadata\":{}},{\"name\":\"path_length\",\"type\":\"long\",\"nullable\":true,\"metadata\":{}},{\"name\":\"k_size\",\"type\":\"long\",\"nullable\":true,\"metadata\":{}}]}","partitionColumns":["instance_name","k_factor","has_closed_cycle","model_name"],"createdTime":1749179031943,"configuration":{}}}
{"add":{"path":"instance_name=pa561.tsp/k_factor=0.75/has_closed_cycle=true/model_name=GeneticAlgorithmNearestNeighborsEnsemble/0-aca0412a-e903-4388-9cf6-08fbf1c6cb09-0.parquet","partitionValues":{"k_factor":"0.75","instance_name":"pa561.tsp","has_closed_cycle":"true","model_name":"GeneticAlgorithmNearestNeighborsEnsemble"},"size":17620,"modificationTime":1749179031942,"dataChange":true,"stats":"{\"numRecords\": 30, \"minValues\": {\"experiment_id\": \"307e50b8-4282-11f0-9af2-7cc25567a3b2\", \"experiment_name\": \"change__all_changes\", \"repetitions\": 30, \"session_id\": \"3a340c92-4282-11f0-9af2-7cc25567a3b2\", \"instance.name\": \"pa561.tsp\", \"instance.number_of_edges\": 157641, \"instance.number_of_vertices\": 561, \"instance.symmetrical_type\": \"TSP\", \"model.name\": \"GeneticAlgorithmNearestNeighborsEnsemble\", \"path_vertices.list.item\": 1, \"path_length\": 2064, \"k_size\": 420}, \"maxValues\": {\"experiment_id\": \"307e50b8-4282-11f0-9af2-7cc25567a3b2\", \"experiment_name\": \"change__all_changes\", \"repetitions\": 30, \"session_id\": \"dff9b2b2-4282-11f0-9af2-7cc25567a3b2\", \"instance.name\": \"pa561.tsp\", \"instance.number_of_edges\": 157641, \"instance.number_of_vertices\": 561, \"instance.symmetrical_type\": \"TSP\", \"model.name\": \"GeneticAlgorithmNearestNeighborsEnsemble\", \"path_vertices.list.item\": 557, \"path_length\": 2064, \"k_size\": 420}, \"nullCount\": {\"experiment_id\": 0, \"experiment_name\": 0, \"repetitions\": 0, \"session_id\": 0, \"instance.name\": 0, \"instance.number_of_edges\": 0, \"instance.number_of_vertices\": 0, \"instance.symmetrical_type\": 0, \"model.name\": 0, \"path_vertices.list.item\": 0, \"path_length\": 0, \"k_size\": 0}}","tags":null,"deletionVector":null,"baseRowId":null,"defaultRowCommitVersion":null,"clusteringProvider":null}}
{"commitInfo":{"timestamp":1749179031943,"operation":"CREATE TABLE","operationParameters":{"mode":"ErrorIfExists","protocol":"{\"minReaderVersion\":1,\"minWriterVersion\":2}","metadata":"{\"configuration\":{},\"createdTime\":1749179031943,\"description\":null,\"format\":{\"options\":{},\"provider\":\"parquet\"},\"id\":\"50a5b5d9-1cd6-4e27-8111-3ca789f93271\",\"name\":null,\"partitionColumns\":[\"instance_name\",\"k_factor\",\"has_closed_cycle\",\"model_name\"],\"schemaString\":\"{\\\"type\\\":\\\"struct\\\",\\\"fields\\\":[{\\\"name\\\":\\\"experiment_id\\\",\\\"type\\\":\\\"string\\\",\\\"nullable\\\":true,\\\"metadata\\\":{}},{\\\"name\\\":\\\"experiment_name\\\",\\\"type\\\":\\\"string\\\",\\\"nullable\\\":true,\\\"metadata\\\":{}},{\\\"name\\\":\\\"instance_name\\\",\\\"type\\\":\\\"string\\\",\\\"nullable\\\":true,\\\"metadata\\\":{}},{\\\"name\\\":\\\"k_factor\\\",\\\"type\\\":\\\"double\\\",\\\"nullable\\\":true,\\\"metadata\\\":{}},{\\\"name\\\":\\\"repetitions\\\",\\\"type\\\":\\\"long\\\",\\\"nullable\\\":true,\\\"metadata\\\":{}},{\\\"name\\\":\\\"model_name\\\",\\\"type\\\":\\\"string\\\",\\\"nullable\\\":true,\\\"metadata\\\":{}},{\\\"name\\\":\\\"has_closed_cycle\\\",\\\"type\\\":\\\"boolean\\\",\\\"nullable\\\":true,\\\"metadata\\\":{}},{\\\"name\\\":\\\"session_id\\\",\\\"type\\\":\\\"string\\\",\\\"nullable\\\":true,\\\"metadata\\\":{}},{\\\"name\\\":\\\"instance\\\",\\\"type\\\":{\\\"type\\\":\\\"struct\\\",\\\"fields\\\":[{\\\"name\\\":\\\"name\\\",\\\"type\\\":\\\"string\\\",\\\"nullable\\\":true,\\\"metadata\\\":{}},{\\\"name\\\":\\\"number_of_edges\\\",\\\"type\\\":\\\"long\\\",\\\"nullable\\\":true,\\\"metadata\\\":{}},{\\\"name\\\":\\\"number_of_vertices\\\",\\\"type\\\":\\\"long\\\",\\\"nullable\\\":true,\\\"metadata\\\":{}},{\\\"name\\\":\\\"symmetrical_type\\\",\\\"type\\\":\\\"string\\\",\\\"nullable\\\":true,\\\"metadata\\\":{}}]},\\\"nullable\\\":true,\\\"metadata\\\":{}},{\\\"name\\\":\\\"model\\\",\\\"type\\\":{\\\"type\\\":\\\"struct\\\",\\\"fields\\\":[{\\\"name\\\":\\\"name\\\",\\\"type\\\":\\\"string\\\",\\\"nullable\\\":true,\\\"metadata\\\":{}}]},\\\"nullable\\\":true,\\\"metadata\\\":{}},{\\\"name\\\":\\\"path_vertices\\\",\\\"type\\\":{\\\"type\\\":\\\"array\\\",\\\"elementType\\\":\\\"long\\\",\\\"containsNull\\\":true},\\\"nullable\\\":true,\\\"metadata\\\":{}},{\\\"name\\\":\\\"path_length\\\",\\\"type\\\":\\\"long\\\",\\\"nullable\\\":true,\\\"metadata\\\":{}},{\\\"name\\\":\\\"k_size\\\",\\\"type\\\":\\\"long\\\",\\\"nullable\\\":true,\\\"metadata\\\":{}}]}\"}","location":"file:///home/leonichel/k-tsp-solver/results/change__all_changes/307e50b8-4282-11f0-9af2-7cc25567a3b2"},"clientVersion":"delta-rs.0.17.3"}}