{"protocol":{"minReaderVersion":1,"minWriterVersion":2}}
{"metaData":{"id":"9907be3d-1ce1-4336-ac5b-510bfb9d41a1","name":null,"description":null,"format":{"provider":"parquet","options":{}},"schemaString":"{\"type\":\"struct\",\"fields\":[{\"name\":\"experiment_id\",\"type\":\"string\",\"nullable\":true,\"metadata\":{}},{\"name\":\"experiment_name\",\"type\":\"string\",\"nullable\":true,\"metadata\":{}},{\"name\":\"instance_name\",\"type\":\"string\",\"nullable\":true,\"metadata\":{}},{\"name\":\"k_factor\",\"type\":\"double\",\"nullable\":true,\"metadata\":{}},{\"name\":\"repetitions\",\"type\":\"long\",\"nullable\":true,\"metadata\":{}},{\"name\":\"model_name\",\"type\":\"string\",\"nullable\":true,\"metadata\":{}},{\"name\":\"has_closed_cycle\",\"type\":\"boolean\",\"nullable\":true,\"metadata\":{}},{\"name\":\"session_id\",\"type\":\"string\",\"nullable\":true,\"metadata\":{}},{\"name\":\"instance\",\"type\":{\"type\":\"struct\",\"fields\":[{\"name\":\"name\",\"type\":\"string\",\"nullable\":true,\"metadata\":{}},{\"name\":\"number_of_edges\",\"type\":\"long\",\"nullable\":true,\"metadata\":{}},{\"name\":\"number_of_vertices\",\"type\":\"long\",\"nullable\":true,\"metadata\":{}},{\"name\":\"symmetrical_type\",\"type\":\"string\",\"nullable\":true,\"metadata\":{}}]},\"nullable\":true,\"metadata\":{}},{\"name\":\"model\",\"type\":{\"type\":\"struct\",\"fields\":[{\"name\":\"name\",\"type\":\"string\",\"nullable\":true,\"metadata\":{}}]},\"nullable\":true,\"metadata\":{}},{\"name\":\"path_vertices\",\"type\":{\"type\":\"array\",\"elementType\":\"long\",\"containsNull\":true},\"nullable\":true,\"metadata\":{}},{\"name\":\"path_length\",\"type\":\"long\",\"nullable\":true,\"metadata\":{}},{\"name\":\"k_size\",\"type\":\"long\",\"nullable\":true,\"metadata\":{}}]}","partitionColumns":[],"createdTime":1747919086872,"configuration":{}}}
{"add":{"path":"0-349a2938-6462-421e-8ec6-1aae83516f58-0.parquet","partitionValues":{},"size":7631,"modificationTime":1747919086871,"dataChange":true,"stats":"{\"numRecords\": 10, \"minValues\": {\"experiment_id\": \"5589112a-370d-11f0-bf3a-b42e99f13130\", \"experiment_name\": \"replacement_operator__ordered_crossover\", \"instance_name\": \"rbg323.atsp\", \"k_factor\": 0.25, \"repetitions\": 10, \"model_name\": \"NearestNeighbors\", \"has_closed_cycle\": true, \"session_id\": \"5625a724-370d-11f0-bf3a-b42e99f13130\", \"instance.name\": \"rbg323.atsp\", \"instance.number_of_edges\": 104329, \"instance.number_of_vertices\": 323, \"instance.symmetrical_type\": \"ATSP\", \"model.name\": \"NearestNeighbors\", \"path_vertices.list.item\": 1, \"path_length\": 226, \"k_size\": 80}, \"maxValues\": {\"experiment_id\": \"5589112a-370d-11f0-bf3a-b42e99f13130\", \"experiment_name\": \"replacement_operator__ordered_crossover\", \"instance_name\": \"rbg323.atsp\", \"k_factor\": 0.25, \"repetitions\": 10, \"model_name\": \"NearestNeighbors\", \"has_closed_cycle\": true, \"session_id\": \"562f611a-370d-11f0-bf3a-b42e99f13130\", \"instance.name\": \"rbg323.atsp\", \"instance.number_of_edges\": 104329, \"instance.number_of_vertices\": 323, \"instance.symmetrical_type\": \"ATSP\", \"model.name\": \"NearestNeighbors\", \"path_vertices.list.item\": 319, \"path_length\": 226, \"k_size\": 80}, \"nullCount\": {\"experiment_id\": 0, \"experiment_name\": 0, \"instance_name\": 0, \"k_factor\": 0, \"repetitions\": 0, \"model_name\": 0, \"has_closed_cycle\": 0, \"session_id\": 0, \"instance.name\": 0, \"instance.number_of_edges\": 0, \"instance.number_of_vertices\": 0, \"instance.symmetrical_type\": 0, \"model.name\": 0, \"path_vertices.list.item\": 0, \"path_length\": 0, \"k_size\": 0}}","tags":null,"deletionVector":null,"baseRowId":null,"defaultRowCommitVersion":null,"clusteringProvider":null}}
{"commitInfo":{"timestamp":1747919086872,"operation":"CREATE TABLE","operationParameters":{"mode":"ErrorIfExists","metadata":"{\"configuration\":{},\"createdTime\":1747919086872,\"description\":null,\"format\":{\"options\":{},\"provider\":\"parquet\"},\"id\":\"9907be3d-1ce1-4336-ac5b-510bfb9d41a1\",\"name\":null,\"partitionColumns\":[],\"schemaString\":\"{\\\"type\\\":\\\"struct\\\",\\\"fields\\\":[{\\\"name\\\":\\\"experiment_id\\\",\\\"type\\\":\\\"string\\\",\\\"nullable\\\":true,\\\"metadata\\\":{}},{\\\"name\\\":\\\"experiment_name\\\",\\\"type\\\":\\\"string\\\",\\\"nullable\\\":true,\\\"metadata\\\":{}},{\\\"name\\\":\\\"instance_name\\\",\\\"type\\\":\\\"string\\\",\\\"nullable\\\":true,\\\"metadata\\\":{}},{\\\"name\\\":\\\"k_factor\\\",\\\"type\\\":\\\"double\\\",\\\"nullable\\\":true,\\\"metadata\\\":{}},{\\\"name\\\":\\\"repetitions\\\",\\\"type\\\":\\\"long\\\",\\\"nullable\\\":true,\\\"metadata\\\":{}},{\\\"name\\\":\\\"model_name\\\",\\\"type\\\":\\\"string\\\",\\\"nullable\\\":true,\\\"metadata\\\":{}},{\\\"name\\\":\\\"has_closed_cycle\\\",\\\"type\\\":\\\"boolean\\\",\\\"nullable\\\":true,\\\"metadata\\\":{}},{\\\"name\\\":\\\"session_id\\\",\\\"type\\\":\\\"string\\\",\\\"nullable\\\":true,\\\"metadata\\\":{}},{\\\"name\\\":\\\"instance\\\",\\\"type\\\":{\\\"type\\\":\\\"struct\\\",\\\"fields\\\":[{\\\"name\\\":\\\"name\\\",\\\"type\\\":\\\"string\\\",\\\"nullable\\\":true,\\\"metadata\\\":{}},{\\\"name\\\":\\\"number_of_edges\\\",\\\"type\\\":\\\"long\\\",\\\"nullable\\\":true,\\\"metadata\\\":{}},{\\\"name\\\":\\\"number_of_vertices\\\",\\\"type\\\":\\\"long\\\",\\\"nullable\\\":true,\\\"metadata\\\":{}},{\\\"name\\\":\\\"symmetrical_type\\\",\\\"type\\\":\\\"string\\\",\\\"nullable\\\":true,\\\"metadata\\\":{}}]},\\\"nullable\\\":true,\\\"metadata\\\":{}},{\\\"name\\\":\\\"model\\\",\\\"type\\\":{\\\"type\\\":\\\"struct\\\",\\\"fields\\\":[{\\\"name\\\":\\\"name\\\",\\\"type\\\":\\\"string\\\",\\\"nullable\\\":true,\\\"metadata\\\":{}}]},\\\"nullable\\\":true,\\\"metadata\\\":{}},{\\\"name\\\":\\\"path_vertices\\\",\\\"type\\\":{\\\"type\\\":\\\"array\\\",\\\"elementType\\\":\\\"long\\\",\\\"containsNull\\\":true},\\\"nullable\\\":true,\\\"metadata\\\":{}},{\\\"name\\\":\\\"path_length\\\",\\\"type\\\":\\\"long\\\",\\\"nullable\\\":true,\\\"metadata\\\":{}},{\\\"name\\\":\\\"k_size\\\",\\\"type\\\":\\\"long\\\",\\\"nullable\\\":true,\\\"metadata\\\":{}}]}\"}","location":"file:///home/leonichel/k-tsp-solver/results/replacement_operator__ordered_crossover/5589112a-370d-11f0-bf3a-b42e99f13130","protocol":"{\"minReaderVersion\":1,\"minWriterVersion\":2}"},"clientVersion":"delta-rs.0.17.3"}}