{"protocol":{"minReaderVersion":1,"minWriterVersion":2}}
{"metaData":{"id":"745ccd61-0b08-44b6-9a92-3e46a9822d31","name":null,"description":null,"format":{"provider":"parquet","options":{}},"schemaString":"{\"type\":\"struct\",\"fields\":[{\"name\":\"experiment_id\",\"type\":\"string\",\"nullable\":true,\"metadata\":{}},{\"name\":\"experiment_name\",\"type\":\"string\",\"nullable\":true,\"metadata\":{}},{\"name\":\"instance_name\",\"type\":\"string\",\"nullable\":true,\"metadata\":{}},{\"name\":\"k_factor\",\"type\":\"double\",\"nullable\":true,\"metadata\":{}},{\"name\":\"repetitions\",\"type\":\"long\",\"nullable\":true,\"metadata\":{}},{\"name\":\"model_name\",\"type\":\"string\",\"nullable\":true,\"metadata\":{}},{\"name\":\"has_closed_cycle\",\"type\":\"boolean\",\"nullable\":true,\"metadata\":{}},{\"name\":\"session_id\",\"type\":\"string\",\"nullable\":true,\"metadata\":{}},{\"name\":\"instance\",\"type\":{\"type\":\"struct\",\"fields\":[{\"name\":\"name\",\"type\":\"string\",\"nullable\":true,\"metadata\":{}},{\"name\":\"number_of_edges\",\"type\":\"long\",\"nullable\":true,\"metadata\":{}},{\"name\":\"number_of_vertices\",\"type\":\"long\",\"nullable\":true,\"metadata\":{}},{\"name\":\"symmetrical_type\",\"type\":\"string\",\"nullable\":true,\"metadata\":{}}]},\"nullable\":true,\"metadata\":{}},{\"name\":\"model\",\"type\":{\"type\":\"struct\",\"fields\":[{\"name\":\"generations\",\"type\":\"long\",\"nullable\":true,\"metadata\":{}},{\"name\":\"mutation_operator_probabilities\",\"type\":{\"type\":\"array\",\"elementType\":\"double\",\"containsNull\":true},\"nullable\":true,\"metadata\":{}},{\"name\":\"mutation_rate\",\"type\":\"double\",\"nullable\":true,\"metadata\":{}},{\"name\":\"name\",\"type\":\"string\",\"nullable\":true,\"metadata\":{}},{\"name\":\"population_size\",\"type\":\"long\",\"nullable\":true,\"metadata\":{}},{\"name\":\"selection_size\",\"type\":\"long\",\"nullable\":true,\"metadata\":{}},{\"name\":\"use_crossover\",\"type\":\"boolean\",\"nullable\":true,\"metadata\":{}}]},\"nullable\":true,\"metadata\":{}},{\"name\":\"path_vertices\",\"type\":{\"type\":\"array\",\"elementType\":\"long\",\"containsNull\":true},\"nullable\":true,\"metadata\":{}},{\"name\":\"path_length\",\"type\":\"long\",\"nullable\":true,\"metadata\":{}},{\"name\":\"k_size\",\"type\":\"long\",\"nullable\":true,\"metadata\":{}}]}","partitionColumns":["instance_name","k_factor","has_closed_cycle","model_name"],"createdTime":1749177244597,"configuration":{}}}
{"add":{"path":"instance_name=rd100.tsp/k_factor=0.25/has_closed_cycle=true/model_name=GeneticAlgorithmNearestNeighborsEnsemble/0-1bf4759c-b772-4771-bc4e-3573040e416b-0.parquet","partitionValues":{"model_name":"GeneticAlgorithmNearestNeighborsEnsemble","has_closed_cycle":"true","instance_name":"rd100.tsp","k_factor":"0.25"},"size":9104,"modificationTime":1749177244597,"dataChange":true,"stats":"{\"numRecords\": 30, \"minValues\": {\"experiment_id\": \"b22cde3a-427e-11f0-a405-7cc25567a3b2\", \"experiment_name\": \"change__replacement_operator__ordered_crossover\", \"repetitions\": 30, \"session_id\": \"b2d0eaca-427e-11f0-a405-7cc25567a3b2\", \"instance.name\": \"rd100.tsp\", \"instance.number_of_edges\": 5050, \"instance.number_of_vertices\": 100, \"instance.symmetrical_type\": \"TSP\", \"model.generations\": 100, \"model.mutation_operator_probabilities.list.item\": 0.25, \"model.mutation_rate\": 0.01, \"model.name\": \"GeneticAlgorithmNearestNeighborsEnsemble\", \"model.population_size\": 100, \"model.selection_size\": 10, \"model.use_crossover\": true, \"path_vertices.list.item\": 1, \"path_length\": 1548, \"k_size\": 25}, \"maxValues\": {\"experiment_id\": \"b22cde3a-427e-11f0-a405-7cc25567a3b2\", \"experiment_name\": \"change__replacement_operator__ordered_crossover\", \"repetitions\": 30, \"session_id\": \"b6a212f0-427e-11f0-a405-7cc25567a3b2\", \"instance.name\": \"rd100.tsp\", \"instance.number_of_edges\": 5050, \"instance.number_of_vertices\": 100, \"instance.symmetrical_type\": \"TSP\", \"model.generations\": 100, \"model.mutation_operator_probabilities.list.item\": 0.25, \"model.mutation_rate\": 0.01, \"model.name\": \"GeneticAlgorithmNearestNeighborsEnsemble\", \"model.population_size\": 100, \"model.selection_size\": 10, \"model.use_crossover\": true, \"path_vertices.list.item\": 97, \"path_length\": 1604, \"k_size\": 25}, \"nullCount\": {\"experiment_id\": 0, \"experiment_name\": 0, \"repetitions\": 0, \"session_id\": 0, \"instance.name\": 0, \"instance.number_of_edges\": 0, \"instance.number_of_vertices\": 0, \"instance.symmetrical_type\": 0, \"model.generations\": 27, \"model.mutation_operator_probabilities.list.item\": 27, \"model.mutation_rate\": 27, \"model.name\": 0, \"model.population_size\": 27, \"model.selection_size\": 27, \"model.use_crossover\": 27, \"path_vertices.list.item\": 0, \"path_length\": 0, \"k_size\": 0}}","tags":null,"deletionVector":null,"baseRowId":null,"defaultRowCommitVersion":null,"clusteringProvider":null}}
{"commitInfo":{"timestamp":1749177244597,"operation":"CREATE TABLE","operationParameters":{"location":"file:///home/leonichel/k-tsp-solver/results/change__replacement_operator__ordered_crossover/b22cde3a-427e-11f0-a405-7cc25567a3b2","mode":"ErrorIfExists","metadata":"{\"configuration\":{},\"createdTime\":1749177244597,\"description\":null,\"format\":{\"options\":{},\"provider\":\"parquet\"},\"id\":\"745ccd61-0b08-44b6-9a92-3e46a9822d31\",\"name\":null,\"partitionColumns\":[\"instance_name\",\"k_factor\",\"has_closed_cycle\",\"model_name\"],\"schemaString\":\"{\\\"type\\\":\\\"struct\\\",\\\"fields\\\":[{\\\"name\\\":\\\"experiment_id\\\",\\\"type\\\":\\\"string\\\",\\\"nullable\\\":true,\\\"metadata\\\":{}},{\\\"name\\\":\\\"experiment_name\\\",\\\"type\\\":\\\"string\\\",\\\"nullable\\\":true,\\\"metadata\\\":{}},{\\\"name\\\":\\\"instance_name\\\",\\\"type\\\":\\\"string\\\",\\\"nullable\\\":true,\\\"metadata\\\":{}},{\\\"name\\\":\\\"k_factor\\\",\\\"type\\\":\\\"double\\\",\\\"nullable\\\":true,\\\"metadata\\\":{}},{\\\"name\\\":\\\"repetitions\\\",\\\"type\\\":\\\"long\\\",\\\"nullable\\\":true,\\\"metadata\\\":{}},{\\\"name\\\":\\\"model_name\\\",\\\"type\\\":\\\"string\\\",\\\"nullable\\\":true,\\\"metadata\\\":{}},{\\\"name\\\":\\\"has_closed_cycle\\\",\\\"type\\\":\\\"boolean\\\",\\\"nullable\\\":true,\\\"metadata\\\":{}},{\\\"name\\\":\\\"session_id\\\",\\\"type\\\":\\\"string\\\",\\\"nullable\\\":true,\\\"metadata\\\":{}},{\\\"name\\\":\\\"instance\\\",\\\"type\\\":{\\\"type\\\":\\\"struct\\\",\\\"fields\\\":[{\\\"name\\\":\\\"name\\\",\\\"type\\\":\\\"string\\\",\\\"nullable\\\":true,\\\"metadata\\\":{}},{\\\"name\\\":\\\"number_of_edges\\\",\\\"type\\\":\\\"long\\\",\\\"nullable\\\":true,\\\"metadata\\\":{}},{\\\"name\\\":\\\"number_of_vertices\\\",\\\"type\\\":\\\"long\\\",\\\"nullable\\\":true,\\\"metadata\\\":{}},{\\\"name\\\":\\\"symmetrical_type\\\",\\\"type\\\":\\\"string\\\",\\\"nullable\\\":true,\\\"metadata\\\":{}}]},\\\"nullable\\\":true,\\\"metadata\\\":{}},{\\\"name\\\":\\\"model\\\",\\\"type\\\":{\\\"type\\\":\\\"struct\\\",\\\"fields\\\":[{\\\"name\\\":\\\"generations\\\",\\\"type\\\":\\\"long\\\",\\\"nullable\\\":true,\\\"metadata\\\":{}},{\\\"name\\\":\\\"mutation_operator_probabilities\\\",\\\"type\\\":{\\\"type\\\":\\\"array\\\",\\\"elementType\\\":\\\"double\\\",\\\"containsNull\\\":true},\\\"nullable\\\":true,\\\"metadata\\\":{}},{\\\"name\\\":\\\"mutation_rate\\\",\\\"type\\\":\\\"double\\\",\\\"nullable\\\":true,\\\"metadata\\\":{}},{\\\"name\\\":\\\"name\\\",\\\"type\\\":\\\"string\\\",\\\"nullable\\\":true,\\\"metadata\\\":{}},{\\\"name\\\":\\\"population_size\\\",\\\"type\\\":\\\"long\\\",\\\"nullable\\\":true,\\\"metadata\\\":{}},{\\\"name\\\":\\\"selection_size\\\",\\\"type\\\":\\\"long\\\",\\\"nullable\\\":true,\\\"metadata\\\":{}},{\\\"name\\\":\\\"use_crossover\\\",\\\"type\\\":\\\"boolean\\\",\\\"nullable\\\":true,\\\"metadata\\\":{}}]},\\\"nullable\\\":true,\\\"metadata\\\":{}},{\\\"name\\\":\\\"path_vertices\\\",\\\"type\\\":{\\\"type\\\":\\\"array\\\",\\\"elementType\\\":\\\"long\\\",\\\"containsNull\\\":true},\\\"nullable\\\":true,\\\"metadata\\\":{}},{\\\"name\\\":\\\"path_length\\\",\\\"type\\\":\\\"long\\\",\\\"nullable\\\":true,\\\"metadata\\\":{}},{\\\"name\\\":\\\"k_size\\\",\\\"type\\\":\\\"long\\\",\\\"nullable\\\":true,\\\"metadata\\\":{}}]}\"}","protocol":"{\"minReaderVersion\":1,\"minWriterVersion\":2}"},"clientVersion":"delta-rs.0.17.3"}}